{"Arkansas County":{"2010":[{"year":2010,"NHWhite":13846,"Black":4712,"American Indian/Alaska Native":35,"Asian":51,"Pacific Islander":0,"NHOther":0,"NHMulti":249,"Hispanic":428,"county":"Arkansas County","state_fips":"05"}],"2020":[{"year":2020,"NHWhite":12246,"Black":4461,"American Indian/Alaska Native":102,"Asian":10,"Pacific Islander":0,"NHOther":0,"NHMulti":344,"Hispanic":598,"county":"Arkansas County","state_fips":"05"}]},"Ashley County":{"2010":[{"year":2010,"NHWhite":15057,"Black":5736,"American Indian/Alaska Native":0,"Asian":20,"Pacific Islander":0,"NHOther":0,"NHMulti":350,"Hispanic":963,"county":"Ashley County","state_fips":"05"}],"2020":[{"year":2020,"NHWhite":13581,"Black":4948,"American Indian/Alaska Native":8,"Asian":34,"Pacific Islander":92,"NHOther":4,"NHMulti":211,"Hispanic":1122,"county":"Ashley County","state_fips":"05"}]},"Baxter County":{"2010":[{"year":2010,"NHWhite":39712,"Black":29,"American Indian/Alaska Native":255,"Asian":186,"Pacific Islander":7,"NHOther":28,"NHMulti":472,"Hispanic":699,"county":"Baxter County","state_fips":"05"}],"2020":[{"year":2020,"NHWhite":38865,"Black":79,"American Indian/Alaska Native":205,"Asian":172,"Pacific Islander":17,"NHOther":91,"NHMulti":1234,"Hispanic":1010,"county":"Baxter County","state_fips":"05"}]},"Benton County":{"2010":[{"year":2010,"NHWhite":163235,"Black":2211,"American Indian/Alaska Native":3277,"Asian":5379,"Pacific Islander":135,"NHOther":496,"NHMulti":4118,"Hispanic":31060,"county":"Benton County","state_fips":"05"}],"2020":[{"year":2020,"NHWhite":192131,"Black":4103,"American Indian/Alaska Native":2929,"Asian":10802,"Pacific Islander":1826,"NHOther":2902,"NHMulti":12990,"Hispanic":45827,"county":"Benton County","state_fips":"05"}]},"Boone County":{"2010":[{"year":2010,"NHWhite":35022,"Black":63,"American Indian/Alaska Native":252,"Asian":185,"Pacific Islander":2,"NHOther":13,"NHMulti":499,"Hispanic":674,"county":"Boone County","state_fips":"05"}],"2020":[{"year":2020,"NHWhite":35174,"Black":80,"American Indian/Alaska Native":250,"Asian":274,"Pacific Islander":0,"NHOther":2,"NHMulti":784,"Hispanic":961,"county":"Boone County","state_fips":"05"}]},"Bradley County":{"2010":[{"year":2010,"NHWhite":6832,"Black":3362,"American Indian/Alaska Native":68,"Asian":0,"Pacific Islander":0,"NHOther":0,"NHMulti":45,"Hispanic":1331,"county":"Bradley County","state_fips":"05"}],"2020":[{"year":2020,"NHWhite":5981,"Black":2970,"American Indian/Alaska Native":0,"Asian":7,"Pacific Islander":0,"NHOther":32,"NHMulti":153,"Hispanic":1662,"county":"Bradley County","state_fips":"05"}]},"Calhoun County":{"2010":[{"year":2010,"NHWhite":4060,"Black":1178,"American Indian/Alaska Native":0,"Asian":0,"Pacific Islander":0,"NHOther":7,"NHMulti":91,"Hispanic":193,"county":"Calhoun County","state_fips":"05"}],"2020":[{"year":2020,"NHWhite":3721,"Black":1133,"American Indian/Alaska Native":0,"Asian":0,"Pacific Islander":15,"NHOther":8,"NHMulti":67,"Hispanic":216,"county":"Calhoun County","state_fips":"05"}]},"Carroll County":{"2010":[{"year":2010,"NHWhite":22754,"Black":137,"American Indian/Alaska Native":209,"Asian":193,"Pacific Islander":0,"NHOther":29,"NHMulti":363,"Hispanic":3286,"county":"Carroll County","state_fips":"05"}],"2020":[{"year":2020,"NHWhite":21984,"Black":70,"American Indian/Alaska Native":298,"Asian":384,"Pacific Islander":277,"NHOther":25,"NHMulti":787,"Hispanic":4237,"county":"Carroll County","state_fips":"05"}]},"Chicot County":{"2010":[{"year":2010,"NHWhite":4868,"Black":6587,"American Indian/Alaska Native":0,"Asian":32,"Pacific Islander":0,"NHOther":0,"NHMulti":134,"Hispanic":481,"county":"Chicot County","state_fips":"05"}],"2020":[{"year":2020,"NHWhite":4051,"Black":5605,"American Indian/Alaska Native":16,"Asian":63,"Pacific Islander":0,"NHOther":0,"NHMulti":99,"Hispanic":599,"county":"Chicot County","state_fips":"05"}]},"Clark County":{"2010":[{"year":2010,"NHWhite":16316,"Black":5322,"American Indian/Alaska Native":63,"Asian":159,"Pacific Islander":0,"NHOther":0,"NHMulti":339,"Hispanic":884,"county":"Clark County","state_fips":"05"}],"2020":[{"year":2020,"NHWhite":15238,"Black":5399,"American Indian/Alaska Native":44,"Asian":142,"Pacific Islander":12,"NHOther":2,"NHMulti":425,"Hispanic":1079,"county":"Clark County","state_fips":"05"}]},"Clay County":{"2010":[{"year":2010,"NHWhite":15803,"Black":18,"American Indian/Alaska Native":122,"Asian":0,"Pacific Islander":0,"NHOther":0,"NHMulti":167,"Hispanic":187,"county":"Clay County","state_fips":"05"}],"2020":[{"year":2020,"NHWhite":13943,"Black":72,"American Indian/Alaska Native":50,"Asian":4,"Pacific Islander":0,"NHOther":0,"NHMulti":316,"Hispanic":325,"county":"Clay County","state_fips":"05"}]},"Cleburne County":{"2010":[{"year":2010,"NHWhite":24623,"Black":144,"American Indian/Alaska Native":95,"Asian":4,"Pacific Islander":7,"NHOther":0,"NHMulti":338,"Hispanic":481,"county":"Cleburne County","state_fips":"05"}],"2020":[{"year":2020,"NHWhite":23523,"Black":227,"American Indian/Alaska Native":222,"Asian":83,"Pacific Islander":0,"NHOther":0,"NHMulti":402,"Hispanic":606,"county":"Cleburne County","state_fips":"05"}]},"Cleveland County":{"2010":[{"year":2010,"NHWhite":7422,"Black":1109,"American Indian/Alaska Native":22,"Asian":0,"Pacific Islander":0,"NHOther":0,"NHMulti":80,"Hispanic":136,"county":"Cleveland County","state_fips":"05"}],"2020":[{"year":2020,"NHWhite":6807,"Black":1087,"American Indian/Alaska Native":23,"Asian":0,"Pacific Islander":0,"NHOther":0,"NHMulti":146,"Hispanic":0,"county":"Cleveland County","state_fips":"05"}]},"Columbia County":{"2010":[{"year":2010,"NHWhite":14733,"Black":9123,"American Indian/Alaska Native":52,"Asian":164,"Pacific Islander":12,"NHOther":0,"NHMulti":180,"Hispanic":492,"county":"Columbia County","state_fips":"05"}],"2020":[{"year":2020,"NHWhite":14003,"Black":8542,"American Indian/Alaska Native":35,"Asian":192,"Pacific Islander":0,"NHOther":14,"NHMulti":184,"Hispanic":650,"county":"Columbia County","state_fips":"05"}]},"Conway County":{"2010":[{"year":2010,"NHWhite":17353,"Black":2507,"American Indian/Alaska Native":122,"Asian":23,"Pacific Islander":0,"NHOther":0,"NHMulti":317,"Hispanic":737,"county":"Conway County","state_fips":"05"}],"2020":[{"year":2020,"NHWhite":17008,"Black":2078,"American Indian/Alaska Native":90,"Asian":98,"Pacific Islander":0,"NHOther":0,"NHMulti":777,"Hispanic":844,"county":"Conway County","state_fips":"05"}]},"Craighead County":{"2010":[{"year":2010,"NHWhite":75626,"Black":11533,"American Indian/Alaska Native":299,"Asian":1055,"Pacific Islander":0,"NHOther":20,"NHMulti":918,"Hispanic":3878,"county":"Craighead County","state_fips":"05"}],"2020":[{"year":2020,"NHWhite":81539,"Black":16525,"American Indian/Alaska Native":198,"Asian":1450,"Pacific Islander":6,"NHOther":365,"NHMulti":3394,"Hispanic":5604,"county":"Craighead County","state_fips":"05"}]},"Crawford County":{"2010":[{"year":2010,"NHWhite":52979,"Black":783,"American Indian/Alaska Native":801,"Asian":884,"Pacific Islander":0,"NHOther":41,"NHMulti":1769,"Hispanic":3521,"county":"Crawford County","state_fips":"05"}],"2020":[{"year":2020,"NHWhite":52859,"Black":957,"American Indian/Alaska Native":938,"Asian":1030,"Pacific Islander":16,"NHOther":158,"NHMulti":2133,"Hispanic":5027,"county":"Crawford County","state_fips":"05"}]},"Crittenden County":{"2010":[{"year":2010,"NHWhite":23332,"Black":25018,"American Indian/Alaska Native":26,"Asian":206,"Pacific Islander":34,"NHOther":31,"NHMulti":990,"Hispanic":1036,"county":"Crittenden County","state_fips":"05"}],"2020":[{"year":2020,"NHWhite":19947,"Black":23398,"American Indian/Alaska Native":87,"Asian":361,"Pacific Islander":22,"NHOther":0,"NHMulti":3255,"Hispanic":1311,"county":"Crittenden County","state_fips":"05"}]},"Cross County":{"2010":[{"year":2010,"NHWhite":13478,"Black":4164,"American Indian/Alaska Native":46,"Asian":0,"Pacific Islander":0,"NHOther":0,"NHMulti":207,"Hispanic":249,"county":"Cross County","state_fips":"05"}],"2020":[{"year":2020,"NHWhite":11973,"Black":2949,"American Indian/Alaska Native":32,"Asian":7,"Pacific Islander":0,"NHOther":8,"NHMulti":1266,"Hispanic":341,"county":"Cross County","state_fips":"05"}]},"Dallas County":{"2010":[{"year":2010,"NHWhite":4503,"Black":3587,"American Indian/Alaska Native":0,"Asian":0,"Pacific Islander":0,"NHOther":10,"NHMulti":9,"Hispanic":171,"county":"Dallas County","state_fips":"05"}],"2020":[{"year":2020,"NHWhite":3760,"Black":3060,"American Indian/Alaska Native":36,"Asian":0,"Pacific Islander":28,"NHOther":0,"NHMulti":113,"Hispanic":117,"county":"Dallas County","state_fips":"05"}]},"Desha County":{"2010":[{"year":2010,"NHWhite":6341,"Black":6230,"American Indian/Alaska Native":94,"Asian":0,"Pacific Islander":0,"NHOther":0,"NHMulti":153,"Hispanic":533,"county":"Desha County","state_fips":"05"}],"2020":[{"year":2020,"NHWhite":5145,"Black":5471,"American Indian/Alaska Native":27,"Asian":46,"Pacific Islander":0,"NHOther":0,"NHMulti":115,"Hispanic":734,"county":"Desha County","state_fips":"05"}]},"Drew County":{"2010":[{"year":2010,"NHWhite":12608,"Black":5304,"American Indian/Alaska Native":0,"Asian":103,"Pacific Islander":0,"NHOther":0,"NHMulti":94,"Hispanic":437,"county":"Drew County","state_fips":"05"}],"2020":[{"year":2020,"NHWhite":12082,"Black":5186,"American Indian/Alaska Native":0,"Asian":5,"Pacific Islander":0,"NHOther":0,"NHMulti":337,"Hispanic":653,"county":"Drew County","state_fips":"05"}]},"Faulkner County":{"2010":[{"year":2010,"NHWhite":90116,"Black":10818,"American Indian/Alaska Native":386,"Asian":1178,"Pacific Islander":30,"NHOther":173,"NHMulti":1751,"Hispanic":3923,"county":"Faulkner County","state_fips":"05"}],"2020":[{"year":2020,"NHWhite":99457,"Black":14252,"American Indian/Alaska Native":422,"Asian":1434,"Pacific Islander":167,"NHOther":511,"NHMulti":3365,"Hispanic":5192,"county":"Faulkner County","state_fips":"05"}]},"Franklin County":{"2010":[{"year":2010,"NHWhite":17071,"Black":50,"American Indian/Alaska Native":147,"Asian":73,"Pacific Islander":0,"NHOther":0,"NHMulti":456,"Hispanic":379,"county":"Franklin County","state_fips":"05"}],"2020":[{"year":2020,"NHWhite":16243,"Black":173,"American Indian/Alaska Native":275,"Asian":133,"Pacific Islander":37,"NHOther":0,"NHMulti":356,"Hispanic":568,"county":"Franklin County","state_fips":"05"}]},"Fulton County":{"2010":[{"year":2010,"NHWhite":11841,"Black":0,"American Indian/Alaska Native":150,"Asian":0,"Pacific Islander":0,"NHOther":0,"NHMulti":172,"Hispanic":100,"county":"Fulton County","state_fips":"05"}],"2020":[{"year":2020,"NHWhite":11620,"Black":41,"American Indian/Alaska Native":67,"Asian":16,"Pacific Islander":26,"NHOther":0,"NHMulti":454,"Hispanic":77,"county":"Fulton County","state_fips":"05"}]},"Garland County":{"2010":[{"year":2010,"NHWhite":80420,"Black":7681,"American Indian/Alaska Native":509,"Asian":777,"Pacific Islander":15,"NHOther":166,"NHMulti":1405,"Hispanic":4317,"county":"Garland County","state_fips":"05"}],"2020":[{"year":2020,"NHWhite":80691,"Black":8258,"American Indian/Alaska Native":934,"Asian":810,"Pacific Islander":39,"NHOther":28,"NHMulti":2584,"Hispanic":5699,"county":"Garland County","state_fips":"05"}]},"Grant County":{"2010":[{"year":2010,"NHWhite":16596,"Black":496,"American Indian/Alaska Native":14,"Asian":14,"Pacific Islander":0,"NHOther":13,"NHMulti":180,"Hispanic":344,"county":"Grant County","state_fips":"05"}],"2020":[{"year":2020,"NHWhite":16850,"Black":458,"American Indian/Alaska Native":17,"Asian":0,"Pacific Islander":29,"NHOther":0,"NHMulti":350,"Hispanic":525,"county":"Grant County","state_fips":"05"}]},"Greene County":{"2010":[{"year":2010,"NHWhite":39482,"Black":273,"American Indian/Alaska Native":224,"Asian":57,"Pacific Islander":0,"NHOther":18,"NHMulti":411,"Hispanic":853,"county":"Greene County","state_fips":"05"}],"2020":[{"year":2020,"NHWhite":41415,"Black":1043,"American Indian/Alaska Native":122,"Asian":169,"Pacific Islander":21,"NHOther":46,"NHMulti":1075,"Hispanic":1306,"county":"Greene County","state_fips":"05"}]},"Hempstead County":{"2010":[{"year":2010,"NHWhite":12929,"Black":6869,"American Indian/Alaska Native":69,"Asian":2,"Pacific Islander":0,"NHOther":8,"NHMulti":289,"Hispanic":2581,"county":"Hempstead County","state_fips":"05"}],"2020":[{"year":2020,"NHWhite":11782,"Black":6504,"American Indian/Alaska Native":89,"Asian":28,"Pacific Islander":73,"NHOther":0,"NHMulti":430,"Hispanic":2789,"county":"Hempstead County","state_fips":"05"}]},"Hot Spring County":{"2010":[{"year":2010,"NHWhite":27612,"Black":3307,"American Indian/Alaska Native":79,"Asian":103,"Pacific Islander":0,"NHOther":0,"NHMulti":711,"Hispanic":859,"county":"Hot Spring County","state_fips":"05"}],"2020":[{"year":2020,"NHWhite":27692,"Black":3785,"American Indian/Alaska Native":95,"Asian":78,"Pacific Islander":6,"NHOther":5,"NHMulti":819,"Hispanic":1187,"county":"Hot Spring County","state_fips":"05"}]},"Howard County":{"2010":[{"year":2010,"NHWhite":9348,"Black":2894,"American Indian/Alaska Native":110,"Asian":43,"Pacific Islander":0,"NHOther":4,"NHMulti":139,"Hispanic":1240,"county":"Howard County","state_fips":"05"}],"2020":[{"year":2020,"NHWhite":8462,"Black":2722,"American Indian/Alaska Native":37,"Asian":116,"Pacific Islander":17,"NHOther":0,"NHMulti":233,"Hispanic":1680,"county":"Howard County","state_fips":"05"}]},"Independence County":{"2010":[{"year":2010,"NHWhite":32576,"Black":735,"American Indian/Alaska Native":168,"Asian":326,"Pacific Islander":12,"NHOther":0,"NHMulti":336,"Hispanic":1841,"county":"Independence County","state_fips":"05"}],"2020":[{"year":2020,"NHWhite":33044,"Black":677,"American Indian/Alaska Native":96,"Asian":287,"Pacific Islander":0,"NHOther":34,"NHMulti":958,"Hispanic":2489,"county":"Independence County","state_fips":"05"}]},"Izard County":{"2010":[{"year":2010,"NHWhite":12969,"Black":209,"American Indian/Alaska Native":17,"Asian":55,"Pacific Islander":0,"NHOther":0,"NHMulti":207,"Hispanic":179,"county":"Izard County","state_fips":"05"}],"2020":[{"year":2020,"NHWhite":12157,"Black":142,"American Indian/Alaska Native":86,"Asian":0,"Pacific Islander":0,"NHOther":17,"NHMulti":868,"Hispanic":326,"county":"Izard County","state_fips":"05"}]},"Jackson County":{"2010":[{"year":2010,"NHWhite":14232,"Black":2984,"American Indian/Alaska Native":108,"Asian":13,"Pacific Islander":9,"NHOther":1,"NHMulti":271,"Hispanic":397,"county":"Jackson County","state_fips":"05"}],"2020":[{"year":2020,"NHWhite":12927,"Black":1949,"American Indian/Alaska Native":15,"Asian":9,"Pacific Islander":6,"NHOther":18,"NHMulti":1483,"Hispanic":501,"county":"Jackson County","state_fips":"05"}]},"Jefferson County":{"2010":[{"year":2010,"NHWhite":33267,"Black":41870,"American Indian/Alaska Native":307,"Asian":626,"Pacific Islander":0,"NHOther":0,"NHMulti":1154,"Hispanic":1223,"county":"Jefferson County","state_fips":"05"}],"2020":[{"year":2020,"NHWhite":26092,"Black":37989,"American Indian/Alaska Native":199,"Asian":671,"Pacific Islander":358,"NHOther":53,"NHMulti":1279,"Hispanic":1482,"county":"Jefferson County","state_fips":"05"}]},"Johnson County":{"2010":[{"year":2010,"NHWhite":21250,"Black":404,"American Indian/Alaska Native":224,"Asian":42,"Pacific Islander":0,"NHOther":4,"NHMulti":386,"Hispanic":2870,"county":"Johnson County","state_fips":"05"}],"2020":[{"year":2020,"NHWhite":20890,"Black":405,"American Indian/Alaska Native":47,"Asian":596,"Pacific Islander":20,"NHOther":83,"NHMulti":734,"Hispanic":3700,"county":"Johnson County","state_fips":"05"}]},"Lafayette County":{"2010":[{"year":2010,"NHWhite":4667,"Black":2929,"American Indian/Alaska Native":6,"Asian":0,"Pacific Islander":5,"NHOther":0,"NHMulti":48,"Hispanic":109,"county":"Lafayette County","state_fips":"05"}],"2020":[{"year":2020,"NHWhite":3931,"Black":2391,"American Indian/Alaska Native":20,"Asian":50,"Pacific Islander":0,"NHOther":29,"NHMulti":109,"Hispanic":198,"county":"Lafayette County","state_fips":"05"}]},"Lawrence County":{"2010":[{"year":2010,"NHWhite":16782,"Black":46,"American Indian/Alaska Native":148,"Asian":0,"Pacific Islander":0,"NHOther":0,"NHMulti":206,"Hispanic":158,"county":"Lawrence County","state_fips":"05"}],"2020":[{"year":2020,"NHWhite":15474,"Black":232,"American Indian/Alaska Native":45,"Asian":11,"Pacific Islander":2,"NHOther":0,"NHMulti":479,"Hispanic":268,"county":"Lawrence County","state_fips":"05"}]},"Lee County":{"2010":[{"year":2010,"NHWhite":4434,"Black":5909,"American Indian/Alaska Native":147,"Asian":28,"Pacific Islander":0,"NHOther":0,"NHMulti":19,"Hispanic":172,"county":"Lee County","state_fips":"05"}],"2020":[{"year":2020,"NHWhite":3663,"Black":4974,"American Indian/Alaska Native":18,"Asian":6,"Pacific Islander":0,"NHOther":0,"NHMulti":57,"Hispanic":245,"county":"Lee County","state_fips":"05"}]},"Lincoln County":{"2010":[{"year":2010,"NHWhite":9284,"Black":4303,"American Indian/Alaska Native":40,"Asian":8,"Pacific Islander":0,"NHOther":0,"NHMulti":200,"Hispanic":368,"county":"Lincoln County","state_fips":"05"}],"2020":[{"year":2020,"NHWhite":8516,"Black":4016,"American Indian/Alaska Native":62,"Asian":0,"Pacific Islander":0,"NHOther":8,"NHMulti":133,"Hispanic":543,"county":"Lincoln County","state_fips":"05"}]},"Little River County":{"2010":[{"year":2010,"NHWhite":9733,"Black":2783,"American Indian/Alaska Native":194,"Asian":0,"Pacific Islander":0,"NHOther":43,"NHMulti":169,"Hispanic":223,"county":"Little River County","state_fips":"05"}],"2020":[{"year":2020,"NHWhite":8982,"Black":2382,"American Indian/Alaska Native":133,"Asian":41,"Pacific Islander":0,"NHOther":0,"NHMulti":352,"Hispanic":455,"county":"Little River County","state_fips":"05"}]},"Logan County":{"2010":[{"year":2010,"NHWhite":20905,"Black":160,"American Indian/Alaska Native":221,"Asian":353,"Pacific Islander":0,"NHOther":22,"NHMulti":378,"Hispanic":541,"county":"Logan County","state_fips":"05"}],"2020":[{"year":2020,"NHWhite":19165,"Black":321,"American Indian/Alaska Native":175,"Asian":344,"Pacific Islander":0,"NHOther":9,"NHMulti":943,"Hispanic":662,"county":"Logan County","state_fips":"05"}]},"Lonoke County":{"2010":[{"year":2010,"NHWhite":58059,"Black":4161,"American Indian/Alaska Native":328,"Asian":408,"Pacific Islander":0,"NHOther":0,"NHMulti":850,"Hispanic":2040,"county":"Lonoke County","state_fips":"05"}],"2020":[{"year":2020,"NHWhite":62525,"Black":3998,"American Indian/Alaska Native":322,"Asian":683,"Pacific Islander":154,"NHOther":66,"NHMulti":2083,"Hispanic":3332,"county":"Lonoke County","state_fips":"05"}]},"Madison County":{"2010":[{"year":2010,"NHWhite":14331,"Black":48,"American Indian/Alaska Native":137,"Asian":73,"Pacific Islander":0,"NHOther":0,"NHMulti":246,"Hispanic":672,"county":"Madison County","state_fips":"05"}],"2020":[{"year":2020,"NHWhite":14472,"Black":17,"American Indian/Alaska Native":83,"Asian":120,"Pacific Islander":102,"NHOther":26,"NHMulti":618,"Hispanic":955,"county":"Madison County","state_fips":"05"}]},"Marion County":{"2010":[{"year":2010,"NHWhite":16091,"Black":0,"American Indian/Alaska Native":177,"Asian":51,"Pacific Islander":0,"NHOther":42,"NHMulti":197,"Hispanic":221,"county":"Marion County","state_fips":"05"}],"2020":[{"year":2020,"NHWhite":15537,"Black":114,"American Indian/Alaska Native":135,"Asian":96,"Pacific Islander":0,"NHOther":0,"NHMulti":312,"Hispanic":392,"county":"Marion County","state_fips":"05"}]},"Miller County":{"2010":[{"year":2010,"NHWhite":30552,"Black":10410,"American Indian/Alaska Native":217,"Asian":265,"Pacific Islander":0,"NHOther":29,"NHMulti":526,"Hispanic":1049,"county":"Miller County","state_fips":"05"}],"2020":[{"year":2020,"NHWhite":29560,"Black":10865,"American Indian/Alaska Native":405,"Asian":126,"Pacific Islander":42,"NHOther":209,"NHMulti":809,"Hispanic":1499,"county":"Miller County","state_fips":"05"}]},"Mississippi County":{"2010":[{"year":2010,"NHWhite":28560,"Black":15797,"American Indian/Alaska Native":35,"Asian":264,"Pacific Islander":0,"NHOther":0,"NHMulti":544,"Hispanic":1615,"county":"Mississippi County","state_fips":"05"}],"2020":[{"year":2020,"NHWhite":23906,"Black":14460,"American Indian/Alaska Native":23,"Asian":195,"Pacific Islander":34,"NHOther":42,"NHMulti":931,"Hispanic":1805,"county":"Mississippi County","state_fips":"05"}]},"Monroe County":{"2010":[{"year":2010,"NHWhite":4780,"Black":3451,"American Indian/Alaska Native":40,"Asian":92,"Pacific Islander":0,"NHOther":0,"NHMulti":6,"Hispanic":123,"county":"Monroe County","state_fips":"05"}],"2020":[{"year":2020,"NHWhite":3708,"Black":2907,"American Indian/Alaska Native":47,"Asian":16,"Pacific Islander":0,"NHOther":0,"NHMulti":126,"Hispanic":75,"county":"Monroe County","state_fips":"05"}]},"Montgomery County":{"2010":[{"year":2010,"NHWhite":8832,"Black":7,"American Indian/Alaska Native":212,"Asian":0,"Pacific Islander":0,"NHOther":0,"NHMulti":128,"Hispanic":311,"county":"Montgomery County","state_fips":"05"}],"2020":[{"year":2020,"NHWhite":8153,"Black":28,"American Indian/Alaska Native":98,"Asian":34,"Pacific Islander":0,"NHOther":0,"NHMulti":265,"Hispanic":386,"county":"Montgomery County","state_fips":"05"}]},"Nevada County":{"2010":[{"year":2010,"NHWhite":5920,"Black":2995,"American Indian/Alaska Native":26,"Asian":45,"Pacific Islander":0,"NHOther":2,"NHMulti":119,"Hispanic":42,"county":"Nevada County","state_fips":"05"}],"2020":[{"year":2020,"NHWhite":5159,"Black":2872,"American Indian/Alaska Native":21,"Asian":5,"Pacific Islander":1,"NHOther":0,"NHMulti":190,"Hispanic":1,"county":"Nevada County","state_fips":"05"}]},"Newton County":{"2010":[{"year":2010,"NHWhite":7978,"Black":28,"American Indian/Alaska Native":37,"Asian":4,"Pacific Islander":0,"NHOther":0,"NHMulti":310,"Hispanic":37,"county":"Newton County","state_fips":"05"}],"2020":[{"year":2020,"NHWhite":7213,"Black":3,"American Indian/Alaska Native":135,"Asian":8,"Pacific Islander":34,"NHOther":0,"NHMulti":288,"Hispanic":72,"county":"Newton County","state_fips":"05"}]},"Ouachita County":{"2010":[{"year":2010,"NHWhite":14816,"Black":10511,"American Indian/Alaska Native":63,"Asian":38,"Pacific Islander":0,"NHOther":0,"NHMulti":451,"Hispanic":414,"county":"Ouachita County","state_fips":"05"}],"2020":[{"year":2020,"NHWhite":12953,"Black":9958,"American Indian/Alaska Native":0,"Asian":10,"Pacific Islander":0,"NHOther":0,"NHMulti":109,"Hispanic":567,"county":"Ouachita County","state_fips":"05"}]},"Perry County":{"2010":[{"year":2010,"NHWhite":9802,"Black":261,"American Indian/Alaska Native":13,"Asian":2,"Pacific Islander":0,"NHOther":0,"NHMulti":158,"Hispanic":199,"county":"Perry County","state_fips":"05"}],"2020":[{"year":2020,"NHWhite":9463,"Black":265,"American Indian/Alaska Native":14,"Asian":6,"Pacific Islander":0,"NHOther":3,"NHMulti":274,"Hispanic":317,"county":"Perry County","state_fips":"05"}]},"Phillips County":{"2010":[{"year":2010,"NHWhite":7819,"Black":14204,"American Indian/Alaska Native":0,"Asian":25,"Pacific Islander":0,"NHOther":0,"NHMulti":87,"Hispanic":277,"county":"Phillips County","state_fips":"05"}],"2020":[{"year":2020,"NHWhite":6183,"Black":11519,"American Indian/Alaska Native":0,"Asian":0,"Pacific Islander":0,"NHOther":3,"NHMulti":91,"Hispanic":355,"county":"Phillips County","state_fips":"05"}]},"Pike County":{"2010":[{"year":2010,"NHWhite":9961,"Black":394,"American Indian/Alaska Native":145,"Asian":13,"Pacific Islander":0,"NHOther":17,"NHMulti":100,"Hispanic":656,"county":"Pike County","state_fips":"05"}],"2020":[{"year":2020,"NHWhite":9242,"Black":408,"American Indian/Alaska Native":48,"Asian":9,"Pacific Islander":0,"NHOther":3,"NHMulti":305,"Hispanic":699,"county":"Pike County","state_fips":"05"}]},"Poinsett County":{"2010":[{"year":2010,"NHWhite":22037,"Black":1713,"American Indian/Alaska Native":74,"Asian":20,"Pacific Islander":29,"NHOther":6,"NHMulti":293,"Hispanic":531,"county":"Poinsett County","state_fips":"05"}],"2020":[{"year":2020,"NHWhite":20364,"Black":888,"American Indian/Alaska Native":12,"Asian":11,"Pacific Islander":0,"NHOther":6,"NHMulti":1704,"Hispanic":762,"county":"Poinsett County","state_fips":"05"}]},"Polk County":{"2010":[{"year":2010,"NHWhite":18537,"Black":42,"American Indian/Alaska Native":345,"Asian":0,"Pacific Islander":8,"NHOther":9,"NHMulti":477,"Hispanic":1072,"county":"Polk County","state_fips":"05"}],"2020":[{"year":2020,"NHWhite":17451,"Black":104,"American Indian/Alaska Native":284,"Asian":61,"Pacific Islander":21,"NHOther":148,"NHMulti":619,"Hispanic":1311,"county":"Polk County","state_fips":"05"}]},"Pope County":{"2010":[{"year":2010,"NHWhite":53090,"Black":1810,"American Indian/Alaska Native":281,"Asian":547,"Pacific Islander":0,"NHOther":78,"NHMulti":1052,"Hispanic":3602,"county":"Pope County","state_fips":"05"}],"2020":[{"year":2020,"NHWhite":53502,"Black":1645,"American Indian/Alaska Native":283,"Asian":714,"Pacific Islander":0,"NHOther":70,"NHMulti":1830,"Hispanic":5882,"county":"Pope County","state_fips":"05"}]},"Prairie County":{"2010":[{"year":2010,"NHWhite":7539,"Black":1181,"American Indian/Alaska Native":37,"Asian":0,"Pacific Islander":0,"NHOther":0,"NHMulti":55,"Hispanic":27,"county":"Prairie County","state_fips":"05"}],"2020":[{"year":2020,"NHWhite":6873,"Black":946,"American Indian/Alaska Native":10,"Asian":14,"Pacific Islander":0,"NHOther":8,"NHMulti":138,"Hispanic":149,"county":"Prairie County","state_fips":"05"}]},"Pulaski County":{"2010":[{"year":2010,"NHWhite":213217,"Black":130198,"American Indian/Alaska Native":1108,"Asian":7342,"Pacific Islander":73,"NHOther":511,"NHMulti":5391,"Hispanic":19220,"county":"Pulaski County","state_fips":"05"}],"2020":[{"year":2020,"NHWhite":202791,"Black":145000,"American Indian/Alaska Native":856,"Asian":8382,"Pacific Islander":144,"NHOther":882,"NHMulti":10809,"Hispanic":24214,"county":"Pulaski County","state_fips":"05"}]},"Randolph County":{"2010":[{"year":2010,"NHWhite":17320,"Black":114,"American Indian/Alaska Native":38,"Asian":103,"Pacific Islander":0,"NHOther":0,"NHMulti":255,"Hispanic":219,"county":"Randolph County","state_fips":"05"}],"2020":[{"year":2020,"NHWhite":16549,"Black":165,"American Indian/Alaska Native":62,"Asian":58,"Pacific Islander":111,"NHOther":0,"NHMulti":594,"Hispanic":395,"county":"Randolph County","state_fips":"05"}]},"Saline County":{"2010":[{"year":2010,"NHWhite":92168,"Black":4319,"American Indian/Alaska Native":585,"Asian":889,"Pacific Islander":16,"NHOther":145,"NHMulti":929,"Hispanic":3388,"county":"Saline County","state_fips":"05"}],"2020":[{"year":2020,"NHWhite":100891,"Black":9211,"American Indian/Alaska Native":270,"Asian":1454,"Pacific Islander":110,"NHOther":168,"NHMulti":2869,"Hispanic":6017,"county":"Saline County","state_fips":"05"}]},"Scott County":{"2010":[{"year":2010,"NHWhite":9661,"Black":0,"American Indian/Alaska Native":42,"Asian":476,"Pacific Islander":0,"NHOther":0,"NHMulti":294,"Hispanic":753,"county":"Scott County","state_fips":"05"}],"2020":[{"year":2020,"NHWhite":8639,"Black":222,"American Indian/Alaska Native":37,"Asian":141,"Pacific Islander":0,"NHOther":0,"NHMulti":422,"Hispanic":808,"county":"Scott County","state_fips":"05"}]},"Searcy County":{"2010":[{"year":2010,"NHWhite":7861,"Black":0,"American Indian/Alaska Native":125,"Asian":33,"Pacific Islander":0,"NHOther":0,"NHMulti":152,"Hispanic":56,"county":"Searcy County","state_fips":"05"}],"2020":[{"year":2020,"NHWhite":7169,"Black":41,"American Indian/Alaska Native":155,"Asian":28,"Pacific Islander":0,"NHOther":0,"NHMulti":296,"Hispanic":209,"county":"Searcy County","state_fips":"05"}]},"Sebastian County":{"2010":[{"year":2010,"NHWhite":91555,"Black":7501,"American Indian/Alaska Native":1055,"Asian":4740,"Pacific Islander":24,"NHOther":112,"NHMulti":4743,"Hispanic":14117,"county":"Sebastian County","state_fips":"05"}],"2020":[{"year":2020,"NHWhite":88206,"Black":7849,"American Indian/Alaska Native":1213,"Asian":5786,"Pacific Islander":14,"NHOther":163,"NHMulti":6042,"Hispanic":18397,"county":"Sebastian County","state_fips":"05"}]},"Sevier County":{"2010":[{"year":2010,"NHWhite":10419,"Black":686,"American Indian/Alaska Native":276,"Asian":120,"Pacific Islander":0,"NHOther":71,"NHMulti":282,"Hispanic":4782,"county":"Sevier County","state_fips":"05"}],"2020":[{"year":2020,"NHWhite":9647,"Black":786,"American Indian/Alaska Native":318,"Asian":82,"Pacific Islander":82,"NHOther":9,"NHMulti":337,"Hispanic":5686,"county":"Sevier County","state_fips":"05"}]},"Sharp County":{"2010":[{"year":2010,"NHWhite":16630,"Black":47,"American Indian/Alaska Native":133,"Asian":0,"Pacific Islander":0,"NHOther":0,"NHMulti":374,"Hispanic":248,"county":"Sharp County","state_fips":"05"}],"2020":[{"year":2020,"NHWhite":15831,"Black":176,"American Indian/Alaska Native":29,"Asian":3,"Pacific Islander":0,"NHOther":0,"NHMulti":766,"Hispanic":412,"county":"Sharp County","state_fips":"05"}]},"St. Francis County":{"2010":[{"year":2010,"NHWhite":12060,"Black":14617,"American Indian/Alaska Native":108,"Asian":66,"Pacific Islander":0,"NHOther":0,"NHMulti":267,"Hispanic":1184,"county":"St. Francis County","state_fips":"05"}],"2020":[{"year":2020,"NHWhite":10039,"Black":13429,"American Indian/Alaska Native":94,"Asian":170,"Pacific Islander":41,"NHOther":0,"NHMulti":348,"Hispanic":1356,"county":"St. Francis County","state_fips":"05"}]},"Statewide":{"2010":[{"year":2010,"NHWhite":2158805,"Black":443320,"American Indian/Alaska Native":17662,"Asian":33075,"Pacific Islander":3985,"NHOther":2737,"NHMulti":44673,"Hispanic":168427,"county":"Statewide","state_fips":"05"}],"2020":[{"year":2020,"NHWhite":2155099,"Black":455485,"American Indian/Alaska Native":15912,"Asian":45389,"Pacific Islander":10258,"NHOther":6974,"NHMulti":93127,"Hispanic":229629,"county":"Statewide","state_fips":"05"}]},"Stone County":{"2010":[{"year":2010,"NHWhite":12063,"Black":0,"American Indian/Alaska Native":7,"Asian":22,"Pacific Islander":0,"NHOther":0,"NHMulti":77,"Hispanic":152,"county":"Stone County","state_fips":"05"}],"2020":[{"year":2020,"NHWhite":11680,"Black":12,"American Indian/Alaska Native":45,"Asian":64,"Pacific Islander":0,"NHOther":0,"NHMulti":536,"Hispanic":245,"county":"Stone County","state_fips":"05"}]},"Union County":{"2010":[{"year":2010,"NHWhite":26315,"Black":13823,"American Indian/Alaska Native":115,"Asian":249,"Pacific Islander":0,"NHOther":0,"NHMulti":372,"Hispanic":1306,"county":"Union County","state_fips":"05"}],"2020":[{"year":2020,"NHWhite":23703,"Black":12878,"American Indian/Alaska Native":231,"Asian":302,"Pacific Islander":0,"NHOther":22,"NHMulti":382,"Hispanic":1571,"county":"Union County","state_fips":"05"}]},"Van Buren County":{"2010":[{"year":2010,"NHWhite":16282,"Black":135,"American Indian/Alaska Native":192,"Asian":7,"Pacific Islander":0,"NHOther":25,"NHMulti":191,"Hispanic":405,"county":"Van Buren County","state_fips":"05"}],"2020":[{"year":2020,"NHWhite":15360,"Black":65,"American Indian/Alaska Native":203,"Asian":22,"Pacific Islander":14,"NHOther":0,"NHMulti":376,"Hispanic":538,"county":"Van Buren County","state_fips":"05"}]},"Washington County":{"2010":[{"year":2010,"NHWhite":148783,"Black":5878,"American Indian/Alaska Native":2348,"Asian":4135,"Pacific Islander":3546,"NHOther":536,"NHMulti":3378,"Hispanic":28588,"county":"Washington County","state_fips":"05"}],"2020":[{"year":2020,"NHWhite":164022,"Black":7915,"American Indian/Alaska Native":1523,"Asian":5962,"Pacific Islander":6242,"NHOther":647,"NHMulti":9989,"Hispanic":39898,"county":"Washington County","state_fips":"05"}]},"White County":{"2010":[{"year":2010,"NHWhite":67561,"Black":2956,"American Indian/Alaska Native":227,"Asian":421,"Pacific Islander":12,"NHOther":27,"NHMulti":1145,"Hispanic":2608,"county":"White County","state_fips":"05"}],"2020":[{"year":2020,"NHWhite":69159,"Black":3352,"American Indian/Alaska Native":339,"Asian":626,"Pacific Islander":0,"NHOther":47,"NHMulti":1705,"Hispanic":3497,"county":"White County","state_fips":"05"}]},"Woodruff County":{"2010":[{"year":2010,"NHWhite":5182,"Black":2197,"American Indian/Alaska Native":6,"Asian":0,"Pacific Islander":9,"NHOther":0,"NHMulti":83,"Hispanic":28,"county":"Woodruff County","state_fips":"05"}],"2020":[{"year":2020,"NHWhite":4505,"Black":1893,"American Indian/Alaska Native":1,"Asian":0,"Pacific Islander":0,"NHOther":0,"NHMulti":63,"Hispanic":15,"county":"Woodruff County","state_fips":"05"}]},"Yell County":{"2010":[{"year":2010,"NHWhite":17007,"Black":259,"American Indian/Alaska Native":24,"Asian":283,"Pacific Islander":0,"NHOther":0,"NHMulti":371,"Hispanic":3951,"county":"Yell County","state_fips":"05"}],"2020":[{"year":2020,"NHWhite":16030,"Black":380,"American Indian/Alaska Native":72,"Asian":238,"Pacific Islander":0,"NHOther":0,"NHMulti":308,"Hispanic":4397,"county":"Yell County","state_fips":"05"}]}}
