{"Accomack County":{"2010":[{"year":2010,"NHWhite":20936,"Black":9729,"American Indian/Alaska Native":30,"Asian":166,"Pacific Islander":0,"NHOther":34,"NHMulti":439,"Hispanic":2732,"county":"Accomack County","state_fips":"51"}],"2020":[{"year":2020,"NHWhite":19505,"Black":9390,"American Indian/Alaska Native":48,"Asian":244,"Pacific Islander":0,"NHOther":48,"NHMulti":445,"Hispanic":2880,"county":"Accomack County","state_fips":"51"}]},"Albemarle County":{"2010":[{"year":2010,"NHWhite":76042,"Black":9387,"American Indian/Alaska Native":168,"Asian":4146,"Pacific Islander":28,"NHOther":251,"NHMulti":1821,"Hispanic":4790,"county":"Albemarle County","state_fips":"51"}],"2020":[{"year":2020,"NHWhite":83403,"Black":9936,"American Indian/Alaska Native":284,"Asian":5902,"Pacific Islander":48,"NHOther":191,"NHMulti":2783,"Hispanic":6272,"county":"Albemarle County","state_fips":"51"}]},"Alexandria city":{"2010":[{"year":2010,"NHWhite":73316,"Black":28478,"American Indian/Alaska Native":349,"Asian":7800,"Pacific Islander":218,"NHOther":362,"NHMulti":3067,"Hispanic":20057,"county":"Alexandria city","state_fips":"51"}],"2020":[{"year":2020,"NHWhite":81674,"Black":33715,"American Indian/Alaska Native":259,"Asian":10490,"Pacific Islander":91,"NHOther":507,"NHMulti":5546,"Hispanic":26027,"county":"Alexandria city","state_fips":"51"}]},"Alleghany County":{"2010":[{"year":2010,"NHWhite":15178,"Black":979,"American Indian/Alaska Native":3,"Asian":81,"Pacific Islander":0,"NHOther":18,"NHMulti":75,"Hispanic":72,"county":"Alleghany County","state_fips":"51"}],"2020":[{"year":2020,"NHWhite":13733,"Black":790,"American Indian/Alaska Native":0,"Asian":10,"Pacific Islander":0,"NHOther":33,"NHMulti":233,"Hispanic":231,"county":"Alleghany County","state_fips":"51"}]},"Amelia County":{"2010":[{"year":2010,"NHWhite":9096,"Black":2954,"American Indian/Alaska Native":31,"Asian":47,"Pacific Islander":18,"NHOther":0,"NHMulti":79,"Hispanic":292,"county":"Amelia County","state_fips":"51"}],"2020":[{"year":2020,"NHWhite":9463,"Black":2871,"American Indian/Alaska Native":0,"Asian":1,"Pacific Islander":0,"NHOther":0,"NHMulti":227,"Hispanic":408,"county":"Amelia County","state_fips":"51"}]},"Amherst County":{"2010":[{"year":2010,"NHWhite":24394,"Black":6093,"American Indian/Alaska Native":301,"Asian":149,"Pacific Islander":0,"NHOther":215,"NHMulti":488,"Hispanic":675,"county":"Amherst County","state_fips":"51"}],"2020":[{"year":2020,"NHWhite":23755,"Black":5747,"American Indian/Alaska Native":243,"Asian":209,"Pacific Islander":12,"NHOther":148,"NHMulti":881,"Hispanic":787,"county":"Amherst County","state_fips":"51"}]},"Appomattox County":{"2010":[{"year":2010,"NHWhite":11182,"Black":3246,"American Indian/Alaska Native":0,"Asian":34,"Pacific Islander":0,"NHOther":44,"NHMulti":111,"Hispanic":36,"county":"Appomattox County","state_fips":"51"}],"2020":[{"year":2020,"NHWhite":12148,"Black":2989,"American Indian/Alaska Native":6,"Asian":31,"Pacific Islander":0,"NHOther":32,"NHMulti":322,"Hispanic":286,"county":"Appomattox County","state_fips":"51"}]},"Arlington County":{"2010":[{"year":2010,"NHWhite":126061,"Black":16668,"American Indian/Alaska Native":416,"Asian":18612,"Pacific Islander":76,"NHOther":1817,"NHMulti":4458,"Hispanic":29359,"county":"Arlington County","state_fips":"51"}],"2020":[{"year":2020,"NHWhite":143786,"Black":21126,"American Indian/Alaska Native":525,"Asian":24308,"Pacific Islander":204,"NHOther":1124,"NHMulti":8869,"Hispanic":36492,"county":"Arlington County","state_fips":"51"}]},"Augusta County":{"2010":[{"year":2010,"NHWhite":67615,"Black":3077,"American Indian/Alaska Native":140,"Asian":334,"Pacific Islander":37,"NHOther":0,"NHMulti":473,"Hispanic":1525,"county":"Augusta County","state_fips":"51"}],"2020":[{"year":2020,"NHWhite":68319,"Black":3164,"American Indian/Alaska Native":155,"Asian":420,"Pacific Islander":73,"NHOther":173,"NHMulti":1177,"Hispanic":2273,"county":"Augusta County","state_fips":"51"}]},"Bath County":{"2010":[{"year":2010,"NHWhite":4513,"Black":172,"American Indian/Alaska Native":0,"Asian":34,"Pacific Islander":0,"NHOther":0,"NHMulti":0,"Hispanic":60,"county":"Bath County","state_fips":"51"}],"2020":[{"year":2020,"NHWhite":3900,"Black":202,"American Indian/Alaska Native":8,"Asian":16,"Pacific Islander":0,"NHOther":0,"NHMulti":89,"Hispanic":33,"county":"Bath County","state_fips":"51"}]},"Bedford city":{"2010":[{"year":2010,"NHWhite":4500,"Black":1357,"American Indian/Alaska Native":0,"Asian":24,"Pacific Islander":0,"NHOther":0,"NHMulti":205,"Hispanic":91,"county":"Bedford city","state_fips":"51"}]},"Bedford County":{"2010":[{"year":2010,"NHWhite":61224,"Black":3784,"American Indian/Alaska Native":126,"Asian":604,"Pacific Islander":10,"NHOther":102,"NHMulti":784,"Hispanic":1063,"county":"Bedford County","state_fips":"51"}],"2020":[{"year":2020,"NHWhite":68785,"Black":5252,"American Indian/Alaska Native":34,"Asian":931,"Pacific Islander":17,"NHOther":228,"NHMulti":1846,"Hispanic":1872,"county":"Bedford County","state_fips":"51"}]},"Bland County":{"2010":[{"year":2010,"NHWhite":6544,"Black":198,"American Indian/Alaska Native":0,"Asian":94,"Pacific Islander":0,"NHOther":0,"NHMulti":16,"Hispanic":21,"county":"Bland County","state_fips":"51"}],"2020":[{"year":2020,"NHWhite":5934,"Black":245,"American Indian/Alaska Native":0,"Asian":13,"Pacific Islander":0,"NHOther":0,"NHMulti":93,"Hispanic":49,"county":"Bland County","state_fips":"51"}]},"Botetourt County":{"2010":[{"year":2010,"NHWhite":30926,"Black":1165,"American Indian/Alaska Native":38,"Asian":179,"Pacific Islander":0,"NHOther":23,"NHMulti":156,"Hispanic":380,"county":"Botetourt County","state_fips":"51"}],"2020":[{"year":2020,"NHWhite":31015,"Black":950,"American Indian/Alaska Native":41,"Asian":219,"Pacific Islander":0,"NHOther":0,"NHMulti":614,"Hispanic":601,"county":"Botetourt County","state_fips":"51"}]},"Bristol city":{"2010":[{"year":2010,"NHWhite":16080,"Black":1178,"American Indian/Alaska Native":0,"Asian":74,"Pacific Islander":0,"NHOther":0,"NHMulti":297,"Hispanic":75,"county":"Bristol city","state_fips":"51"}],"2020":[{"year":2020,"NHWhite":14936,"Black":1213,"American Indian/Alaska Native":0,"Asian":33,"Pacific Islander":5,"NHOther":131,"NHMulti":663,"Hispanic":78,"county":"Bristol city","state_fips":"51"}]},"Brunswick County":{"2010":[{"year":2010,"NHWhite":7109,"Black":10390,"American Indian/Alaska Native":0,"Asian":28,"Pacific Islander":0,"NHOther":0,"NHMulti":88,"Hispanic":92,"county":"Brunswick County","state_fips":"51"}],"2020":[{"year":2020,"NHWhite":6630,"Black":8827,"American Indian/Alaska Native":9,"Asian":26,"Pacific Islander":0,"NHOther":0,"NHMulti":453,"Hispanic":391,"county":"Brunswick County","state_fips":"51"}]},"Buchanan County":{"2010":[{"year":2010,"NHWhite":23552,"Black":492,"American Indian/Alaska Native":211,"Asian":151,"Pacific Islander":0,"NHOther":0,"NHMulti":13,"Hispanic":40,"county":"Buchanan County","state_fips":"51"}],"2020":[{"year":2020,"NHWhite":20240,"Black":531,"American Indian/Alaska Native":166,"Asian":57,"Pacific Islander":0,"NHOther":41,"NHMulti":169,"Hispanic":170,"county":"Buchanan County","state_fips":"51"}]},"Buckingham County":{"2010":[{"year":2010,"NHWhite":10283,"Black":6278,"American Indian/Alaska Native":53,"Asian":33,"Pacific Islander":0,"NHOther":0,"NHMulti":105,"Hispanic":122,"county":"Buckingham County","state_fips":"51"}],"2020":[{"year":2020,"NHWhite":10451,"Black":5521,"American Indian/Alaska Native":122,"Asian":13,"Pacific Islander":0,"NHOther":70,"NHMulti":492,"Hispanic":418,"county":"Buckingham County","state_fips":"51"}]},"Buena Vista city":{"2010":[{"year":2010,"NHWhite":6044,"Black":400,"American Indian/Alaska Native":23,"Asian":0,"Pacific Islander":8,"NHOther":10,"NHMulti":109,"Hispanic":59,"county":"Buena Vista city","state_fips":"51"}],"2020":[{"year":2020,"NHWhite":5690,"Black":389,"American Indian/Alaska Native":7,"Asian":23,"Pacific Islander":20,"NHOther":7,"NHMulti":249,"Hispanic":92,"county":"Buena Vista city","state_fips":"51"}]},"Campbell County":{"2010":[{"year":2010,"NHWhite":44138,"Black":7593,"American Indian/Alaska Native":118,"Asian":385,"Pacific Islander":0,"NHOther":67,"NHMulti":931,"Hispanic":942,"county":"Campbell County","state_fips":"51"}],"2020":[{"year":2020,"NHWhite":43814,"Black":7788,"American Indian/Alaska Native":112,"Asian":518,"Pacific Islander":10,"NHOther":90,"NHMulti":1569,"Hispanic":1505,"county":"Campbell County","state_fips":"51"}]},"Caroline County":{"2010":[{"year":2010,"NHWhite":17728,"Black":8129,"American Indian/Alaska Native":122,"Asian":127,"Pacific Islander":28,"NHOther":42,"NHMulti":694,"Hispanic":974,"county":"Caroline County","state_fips":"51"}],"2020":[{"year":2020,"NHWhite":19317,"Black":8098,"American Indian/Alaska Native":109,"Asian":177,"Pacific Islander":0,"NHOther":158,"NHMulti":1181,"Hispanic":1541,"county":"Caroline County","state_fips":"51"}]},"Carroll County":{"2010":[{"year":2010,"NHWhite":28823,"Black":361,"American Indian/Alaska Native":36,"Asian":32,"Pacific Islander":0,"NHOther":0,"NHMulti":314,"Hispanic":419,"county":"Carroll County","state_fips":"51"}],"2020":[{"year":2020,"NHWhite":28176,"Black":135,"American Indian/Alaska Native":119,"Asian":0,"Pacific Islander":5,"NHOther":14,"NHMulti":343,"Hispanic":1119,"county":"Carroll County","state_fips":"51"}]},"Charles City County":{"2010":[{"year":2010,"NHWhite":2952,"Black":3544,"American Indian/Alaska Native":437,"Asian":13,"Pacific Islander":0,"NHOther":0,"NHMulti":148,"Hispanic":111,"county":"Charles City County","state_fips":"51"}],"2020":[{"year":2020,"NHWhite":2981,"Black":3052,"American Indian/Alaska Native":414,"Asian":63,"Pacific Islander":0,"NHOther":15,"NHMulti":305,"Hispanic":135,"county":"Charles City County","state_fips":"51"}]},"Charlotte County":{"2010":[{"year":2010,"NHWhite":8401,"Black":4039,"American Indian/Alaska Native":72,"Asian":0,"Pacific Islander":0,"NHOther":0,"NHMulti":63,"Hispanic":69,"county":"Charlotte County","state_fips":"51"}],"2020":[{"year":2020,"NHWhite":8119,"Black":3318,"American Indian/Alaska Native":30,"Asian":43,"Pacific Islander":0,"NHOther":0,"NHMulti":169,"Hispanic":274,"county":"Charlotte County","state_fips":"51"}]},"Charlottesville city":{"2010":[{"year":2010,"NHWhite":28103,"Black":8326,"American Indian/Alaska Native":36,"Asian":2739,"Pacific Islander":18,"NHOther":20,"NHMulti":1024,"Hispanic":2001,"county":"Charlottesville city","state_fips":"51"}],"2020":[{"year":2020,"NHWhite":30973,"Black":8716,"American Indian/Alaska Native":122,"Asian":3313,"Pacific Islander":5,"NHOther":157,"NHMulti":1308,"Hispanic":2623,"county":"Charlottesville city","state_fips":"51"}]},"Chesapeake city":{"2010":[{"year":2010,"NHWhite":134185,"Black":64481,"American Indian/Alaska Native":730,"Asian":6167,"Pacific Islander":55,"NHOther":698,"NHMulti":4330,"Hispanic":8622,"county":"Chesapeake city","state_fips":"51"}],"2020":[{"year":2020,"NHWhite":136878,"Black":70466,"American Indian/Alaska Native":346,"Asian":8057,"Pacific Islander":23,"NHOther":996,"NHMulti":10068,"Hispanic":15813,"county":"Chesapeake city","state_fips":"51"}]},"Chesterfield County":{"2010":[{"year":2010,"NHWhite":206443,"Black":65155,"American Indian/Alaska Native":949,"Asian":10252,"Pacific Islander":135,"NHOther":772,"NHMulti":4815,"Hispanic":20112,"county":"Chesterfield County","state_fips":"51"}],"2020":[{"year":2020,"NHWhite":212226,"Black":78805,"American Indian/Alaska Native":763,"Asian":11809,"Pacific Islander":86,"NHOther":1367,"NHMulti":11726,"Hispanic":31718,"county":"Chesterfield County","state_fips":"51"}]},"Clarke County":{"2010":[{"year":2010,"NHWhite":12366,"Black":735,"American Indian/Alaska Native":32,"Asian":114,"Pacific Islander":0,"NHOther":31,"NHMulti":239,"Hispanic":496,"county":"Clarke County","state_fips":"51"}],"2020":[{"year":2020,"NHWhite":12373,"Black":716,"American Indian/Alaska Native":0,"Asian":217,"Pacific Islander":0,"NHOther":78,"NHMulti":272,"Hispanic":842,"county":"Clarke County","state_fips":"51"}]},"Colonial Heights city":{"2010":[{"year":2010,"NHWhite":14251,"Black":1829,"American Indian/Alaska Native":33,"Asian":532,"Pacific Islander":0,"NHOther":0,"NHMulti":184,"Hispanic":643,"county":"Colonial Heights city","state_fips":"51"}],"2020":[{"year":2020,"NHWhite":12338,"Black":2713,"American Indian/Alaska Native":54,"Asian":636,"Pacific Islander":0,"NHOther":10,"NHMulti":437,"Hispanic":1095,"county":"Colonial Heights city","state_fips":"51"}]},"Covington city":{"2010":[{"year":2010,"NHWhite":4989,"Black":700,"American Indian/Alaska Native":17,"Asian":68,"Pacific Islander":0,"NHOther":0,"NHMulti":159,"Hispanic":56,"county":"Covington city","state_fips":"51"}],"2020":[{"year":2020,"NHWhite":4550,"Black":706,"American Indian/Alaska Native":0,"Asian":65,"Pacific Islander":0,"NHOther":0,"NHMulti":181,"Hispanic":151,"county":"Covington city","state_fips":"51"}]},"Craig County":{"2010":[{"year":2010,"NHWhite":5079,"Black":35,"American Indian/Alaska Native":0,"Asian":4,"Pacific Islander":0,"NHOther":0,"NHMulti":55,"Hispanic":0,"county":"Craig County","state_fips":"51"}],"2020":[{"year":2020,"NHWhite":5012,"Black":2,"American Indian/Alaska Native":0,"Asian":0,"Pacific Islander":0,"NHOther":0,"NHMulti":88,"Hispanic":1,"county":"Craig County","state_fips":"51"}]},"Culpeper County":{"2010":[{"year":2010,"NHWhite":33077,"Black":7148,"American Indian/Alaska Native":83,"Asian":570,"Pacific Islander":0,"NHOther":80,"NHMulti":936,"Hispanic":3855,"county":"Culpeper County","state_fips":"51"}],"2020":[{"year":2020,"NHWhite":35831,"Black":6646,"American Indian/Alaska Native":226,"Asian":854,"Pacific Islander":67,"NHOther":267,"NHMulti":2207,"Hispanic":5837,"county":"Culpeper County","state_fips":"51"}]},"Cumberland County":{"2010":[{"year":2010,"NHWhite":6190,"Black":3254,"American Indian/Alaska Native":12,"Asian":0,"Pacific Islander":23,"NHOther":4,"NHMulti":183,"Hispanic":189,"county":"Cumberland County","state_fips":"51"}],"2020":[{"year":2020,"NHWhite":6256,"Black":3216,"American Indian/Alaska Native":9,"Asian":102,"Pacific Islander":0,"NHOther":0,"NHMulti":181,"Hispanic":105,"county":"Cumberland County","state_fips":"51"}]},"Danville city":{"2010":[{"year":2010,"NHWhite":20862,"Black":21033,"American Indian/Alaska Native":73,"Asian":353,"Pacific Islander":8,"NHOther":21,"NHMulti":285,"Hispanic":1152,"county":"Danville city","state_fips":"51"}],"2020":[{"year":2020,"NHWhite":16917,"Black":19720,"American Indian/Alaska Native":41,"Asian":514,"Pacific Islander":44,"NHOther":46,"NHMulti":1569,"Hispanic":1817,"county":"Danville city","state_fips":"51"}]},"Dickenson County":{"2010":[{"year":2010,"NHWhite":15718,"Black":71,"American Indian/Alaska Native":11,"Asian":4,"Pacific Islander":0,"NHOther":0,"NHMulti":138,"Hispanic":24,"county":"Dickenson County","state_fips":"51"}],"2020":[{"year":2020,"NHWhite":14156,"Black":83,"American Indian/Alaska Native":5,"Asian":16,"Pacific Islander":0,"NHOther":5,"NHMulti":118,"Hispanic":141,"county":"Dickenson County","state_fips":"51"}]},"Dinwiddie County":{"2010":[{"year":2010,"NHWhite":17361,"Black":8926,"American Indian/Alaska Native":86,"Asian":155,"Pacific Islander":0,"NHOther":32,"NHMulti":238,"Hispanic":651,"county":"Dinwiddie County","state_fips":"51"}],"2020":[{"year":2020,"NHWhite":17802,"Black":9113,"American Indian/Alaska Native":0,"Asian":260,"Pacific Islander":27,"NHOther":151,"NHMulti":295,"Hispanic":1038,"county":"Dinwiddie County","state_fips":"51"}]},"Emporia city":{"2010":[{"year":2010,"NHWhite":1876,"Black":3641,"American Indian/Alaska Native":23,"Asian":34,"Pacific Islander":0,"NHOther":0,"NHMulti":29,"Hispanic":219,"county":"Emporia city","state_fips":"51"}],"2020":[{"year":2020,"NHWhite":1443,"Black":3217,"American Indian/Alaska Native":3,"Asian":0,"Pacific Islander":0,"NHOther":4,"NHMulti":402,"Hispanic":339,"county":"Emporia city","state_fips":"51"}]},"Essex County":{"2010":[{"year":2010,"NHWhite":6158,"Black":4202,"American Indian/Alaska Native":87,"Asian":20,"Pacific Islander":11,"NHOther":0,"NHMulti":145,"Hispanic":278,"county":"Essex County","state_fips":"51"}],"2020":[{"year":2020,"NHWhite":5995,"Black":4276,"American Indian/Alaska Native":0,"Asian":63,"Pacific Islander":0,"NHOther":0,"NHMulti":210,"Hispanic":416,"county":"Essex County","state_fips":"51"}]},"Fairfax city":{"2010":[{"year":2010,"NHWhite":13862,"Black":1019,"American Indian/Alaska Native":108,"Asian":3372,"Pacific Islander":32,"NHOther":36,"NHMulti":434,"Hispanic":3195,"county":"Fairfax city","state_fips":"51"}],"2020":[{"year":2020,"NHWhite":12918,"Black":1198,"American Indian/Alaska Native":0,"Asian":4312,"Pacific Islander":0,"NHOther":11,"NHMulti":835,"Hispanic":4038,"county":"Fairfax city","state_fips":"51"}]},"Fairfax County":{"2010":[{"year":2010,"NHWhite":591054,"Black":92436,"American Indian/Alaska Native":1964,"Asian":180829,"Pacific Islander":801,"NHOther":4246,"NHMulti":24251,"Hispanic":152973,"county":"Fairfax County","state_fips":"51"}],"2020":[{"year":2020,"NHWhite":574760,"Black":108847,"American Indian/Alaska Native":1543,"Asian":226465,"Pacific Islander":718,"NHOther":5035,"NHMulti":45391,"Hispanic":186680,"county":"Fairfax County","state_fips":"51"}]},"Falls Church city":{"2010":[{"year":2010,"NHWhite":8557,"Black":516,"American Indian/Alaska Native":12,"Asian":1211,"Pacific Islander":0,"NHOther":39,"NHMulti":152,"Hispanic":978,"county":"Falls Church city","state_fips":"51"}],"2020":[{"year":2020,"NHWhite":10183,"Black":654,"American Indian/Alaska Native":0,"Asian":1414,"Pacific Islander":0,"NHOther":12,"NHMulti":523,"Hispanic":1523,"county":"Falls Church city","state_fips":"51"}]},"Fauquier County":{"2010":[{"year":2010,"NHWhite":53119,"Black":5374,"American Indian/Alaska Native":263,"Asian":872,"Pacific Islander":0,"NHOther":162,"NHMulti":814,"Hispanic":3942,"county":"Fauquier County","state_fips":"51"}],"2020":[{"year":2020,"NHWhite":55909,"Black":5085,"American Indian/Alaska Native":261,"Asian":1262,"Pacific Islander":25,"NHOther":100,"NHMulti":1629,"Hispanic":6082,"county":"Fauquier County","state_fips":"51"}]},"Floyd County":{"2010":[{"year":2010,"NHWhite":14205,"Black":234,"American Indian/Alaska Native":72,"Asian":55,"Pacific Islander":0,"NHOther":0,"NHMulti":117,"Hispanic":347,"county":"Floyd County","state_fips":"51"}],"2020":[{"year":2020,"NHWhite":14699,"Black":257,"American Indian/Alaska Native":105,"Asian":42,"Pacific Islander":0,"NHOther":9,"NHMulti":197,"Hispanic":457,"county":"Floyd County","state_fips":"51"}]},"Fluvanna County":{"2010":[{"year":2010,"NHWhite":20061,"Black":3903,"American Indian/Alaska Native":67,"Asian":151,"Pacific Islander":0,"NHOther":0,"NHMulti":405,"Hispanic":721,"county":"Fluvanna County","state_fips":"51"}],"2020":[{"year":2020,"NHWhite":20828,"Black":3879,"American Indian/Alaska Native":40,"Asian":179,"Pacific Islander":26,"NHOther":129,"NHMulti":826,"Hispanic":966,"county":"Fluvanna County","state_fips":"51"}]},"Franklin city":{"2010":[{"year":2010,"NHWhite":3480,"Black":4827,"American Indian/Alaska Native":8,"Asian":61,"Pacific Islander":0,"NHOther":0,"NHMulti":151,"Hispanic":22,"county":"Franklin city","state_fips":"51"}],"2020":[{"year":2020,"NHWhite":2983,"Black":4377,"American Indian/Alaska Native":0,"Asian":187,"Pacific Islander":0,"NHOther":0,"NHMulti":227,"Hispanic":241,"county":"Franklin city","state_fips":"51"}]},"Franklin County":{"2010":[{"year":2010,"NHWhite":48102,"Black":4666,"American Indian/Alaska Native":0,"Asian":185,"Pacific Islander":0,"NHOther":59,"NHMulti":585,"Hispanic":1341,"county":"Franklin County","state_fips":"51"}],"2020":[{"year":2020,"NHWhite":48970,"Black":4366,"American Indian/Alaska Native":149,"Asian":335,"Pacific Islander":5,"NHOther":54,"NHMulti":770,"Hispanic":1582,"county":"Franklin County","state_fips":"51"}]},"Frederick County":{"2010":[{"year":2010,"NHWhite":65473,"Black":2997,"American Indian/Alaska Native":106,"Asian":936,"Pacific Islander":136,"NHOther":408,"NHMulti":908,"Hispanic":4871,"county":"Frederick County","state_fips":"51"}],"2020":[{"year":2020,"NHWhite":72947,"Black":3305,"American Indian/Alaska Native":148,"Asian":1333,"Pacific Islander":42,"NHOther":17,"NHMulti":2366,"Hispanic":7896,"county":"Frederick County","state_fips":"51"}]},"Fredericksburg city":{"2010":[{"year":2010,"NHWhite":14672,"Black":5368,"American Indian/Alaska Native":109,"Asian":617,"Pacific Islander":14,"NHOther":127,"NHMulti":306,"Hispanic":2162,"county":"Fredericksburg city","state_fips":"51"}],"2020":[{"year":2020,"NHWhite":16879,"Black":5350,"American Indian/Alaska Native":63,"Asian":1114,"Pacific Islander":17,"NHOther":77,"NHMulti":2334,"Hispanic":3225,"county":"Fredericksburg city","state_fips":"51"}]},"Galax city":{"2010":[{"year":2010,"NHWhite":5555,"Black":306,"American Indian/Alaska Native":112,"Asian":0,"Pacific Islander":0,"NHOther":0,"NHMulti":0,"Hispanic":963,"county":"Galax city","state_fips":"51"}],"2020":[{"year":2020,"NHWhite":4649,"Black":423,"American Indian/Alaska Native":0,"Asian":22,"Pacific Islander":49,"NHOther":17,"NHMulti":28,"Hispanic":1214,"county":"Galax city","state_fips":"51"}]},"Giles County":{"2010":[{"year":2010,"NHWhite":16552,"Black":197,"American Indian/Alaska Native":0,"Asian":0,"Pacific Islander":0,"NHOther":0,"NHMulti":277,"Hispanic":179,"county":"Giles County","state_fips":"51"}],"2020":[{"year":2020,"NHWhite":15861,"Black":304,"American Indian/Alaska Native":0,"Asian":79,"Pacific Islander":29,"NHOther":0,"NHMulti":186,"Hispanic":301,"county":"Giles County","state_fips":"51"}]},"Gloucester County":{"2010":[{"year":2010,"NHWhite":31316,"Black":3361,"American Indian/Alaska Native":246,"Asian":289,"Pacific Islander":0,"NHOther":96,"NHMulti":339,"Hispanic":963,"county":"Gloucester County","state_fips":"51"}],"2020":[{"year":2020,"NHWhite":31492,"Black":3637,"American Indian/Alaska Native":0,"Asian":287,"Pacific Islander":0,"NHOther":46,"NHMulti":521,"Hispanic":1379,"county":"Gloucester County","state_fips":"51"}]},"Goochland County":{"2010":[{"year":2010,"NHWhite":14544,"Black":5892,"American Indian/Alaska Native":51,"Asian":33,"Pacific Islander":0,"NHOther":48,"NHMulti":142,"Hispanic":426,"county":"Goochland County","state_fips":"51"}],"2020":[{"year":2020,"NHWhite":18203,"Black":3444,"American Indian/Alaska Native":4,"Asian":362,"Pacific Islander":0,"NHOther":42,"NHMulti":730,"Hispanic":687,"county":"Goochland County","state_fips":"51"}]},"Grayson County":{"2010":[{"year":2010,"NHWhite":14960,"Black":384,"American Indian/Alaska Native":0,"Asian":3,"Pacific Islander":83,"NHOther":0,"NHMulti":42,"Hispanic":383,"county":"Grayson County","state_fips":"51"}],"2020":[{"year":2020,"NHWhite":14006,"Black":834,"American Indian/Alaska Native":8,"Asian":157,"Pacific Islander":0,"NHOther":0,"NHMulti":87,"Hispanic":559,"county":"Grayson County","state_fips":"51"}]},"Greene County":{"2010":[{"year":2010,"NHWhite":15623,"Black":1255,"American Indian/Alaska Native":0,"Asian":172,"Pacific Islander":0,"NHOther":33,"NHMulti":298,"Hispanic":701,"county":"Greene County","state_fips":"51"}],"2020":[{"year":2020,"NHWhite":16001,"Black":1297,"American Indian/Alaska Native":42,"Asian":407,"Pacific Islander":0,"NHOther":272,"NHMulti":539,"Hispanic":1176,"county":"Greene County","state_fips":"51"}]},"Greensville County":{"2010":[{"year":2010,"NHWhite":4584,"Black":7318,"American Indian/Alaska Native":34,"Asian":66,"Pacific Islander":0,"NHOther":7,"NHMulti":18,"Hispanic":154,"county":"Greensville County","state_fips":"51"}],"2020":[{"year":2020,"NHWhite":4125,"Black":6556,"American Indian/Alaska Native":6,"Asian":7,"Pacific Islander":0,"NHOther":7,"NHMulti":420,"Hispanic":282,"county":"Greensville County","state_fips":"51"}]},"Halifax County":{"2010":[{"year":2010,"NHWhite":21798,"Black":13406,"American Indian/Alaska Native":45,"Asian":120,"Pacific Islander":18,"NHOther":0,"NHMulti":326,"Hispanic":598,"county":"Halifax County","state_fips":"51"}],"2020":[{"year":2020,"NHWhite":20486,"Black":11803,"American Indian/Alaska Native":85,"Asian":253,"Pacific Islander":0,"NHOther":0,"NHMulti":939,"Hispanic":729,"county":"Halifax County","state_fips":"51"}]},"Hampton city":{"2010":[{"year":2010,"NHWhite":58704,"Black":67540,"American Indian/Alaska Native":626,"Asian":3277,"Pacific Islander":119,"NHOther":285,"NHMulti":2504,"Hispanic":5991,"county":"Hampton city","state_fips":"51"}],"2020":[{"year":2020,"NHWhite":50636,"Black":66701,"American Indian/Alaska Native":552,"Asian":3031,"Pacific Islander":162,"NHOther":503,"NHMulti":5376,"Hispanic":8208,"county":"Hampton city","state_fips":"51"}]},"Hanover County":{"2010":[{"year":2010,"NHWhite":85061,"Black":8974,"American Indian/Alaska Native":286,"Asian":1194,"Pacific Islander":76,"NHOther":135,"NHMulti":1399,"Hispanic":2047,"county":"Hanover County","state_fips":"51"}],"2020":[{"year":2020,"NHWhite":88873,"Black":9174,"American Indian/Alaska Native":314,"Asian":1697,"Pacific Islander":79,"NHOther":282,"NHMulti":2847,"Hispanic":3272,"county":"Hanover County","state_fips":"51"}]},"Harrisonburg city":{"2010":[{"year":2010,"NHWhite":34986,"Black":2955,"American Indian/Alaska Native":65,"Asian":1844,"Pacific Islander":87,"NHOther":49,"NHMulti":581,"Hispanic":6839,"county":"Harrisonburg city","state_fips":"51"}],"2020":[{"year":2020,"NHWhite":34955,"Black":3722,"American Indian/Alaska Native":0,"Asian":1821,"Pacific Islander":0,"NHOther":281,"NHMulti":2065,"Hispanic":10714,"county":"Harrisonburg city","state_fips":"51"}]},"Henrico County":{"2010":[{"year":2010,"NHWhite":175944,"Black":84919,"American Indian/Alaska Native":914,"Asian":18356,"Pacific Islander":101,"NHOther":868,"NHMulti":5598,"Hispanic":13353,"county":"Henrico County","state_fips":"51"}],"2020":[{"year":2020,"NHWhite":172663,"Black":97057,"American Indian/Alaska Native":437,"Asian":29667,"Pacific Islander":89,"NHOther":779,"NHMulti":10301,"Hispanic":19083,"county":"Henrico County","state_fips":"51"}]},"Henry County":{"2010":[{"year":2010,"NHWhite":39325,"Black":12202,"American Indian/Alaska Native":0,"Asian":206,"Pacific Islander":0,"NHOther":20,"NHMulti":636,"Hispanic":2471,"county":"Henry County","state_fips":"51"}],"2020":[{"year":2020,"NHWhite":35486,"Black":11367,"American Indian/Alaska Native":28,"Asian":316,"Pacific Islander":0,"NHOther":42,"NHMulti":926,"Hispanic":2867,"county":"Henry County","state_fips":"51"}]},"Highland County":{"2010":[{"year":2010,"NHWhite":2355,"Black":0,"American Indian/Alaska Native":0,"Asian":0,"Pacific Islander":0,"NHOther":0,"NHMulti":34,"Hispanic":6,"county":"Highland County","state_fips":"51"}],"2020":[{"year":2020,"NHWhite":2112,"Black":0,"American Indian/Alaska Native":0,"Asian":80,"Pacific Islander":0,"NHOther":0,"NHMulti":10,"Hispanic":0,"county":"Highland County","state_fips":"51"}]},"Hopewell city":{"2010":[{"year":2010,"NHWhite":12325,"Black":8537,"American Indian/Alaska Native":0,"Asian":123,"Pacific Islander":0,"NHOther":0,"NHMulti":236,"Hispanic":1285,"county":"Hopewell city","state_fips":"51"}],"2020":[{"year":2020,"NHWhite":10169,"Black":9521,"American Indian/Alaska Native":26,"Asian":309,"Pacific Islander":0,"NHOther":21,"NHMulti":563,"Hispanic":1891,"county":"Hopewell city","state_fips":"51"}]},"Isle of Wight County":{"2010":[{"year":2010,"NHWhite":24645,"Black":8674,"American Indian/Alaska Native":31,"Asian":200,"Pacific Islander":0,"NHOther":10,"NHMulti":525,"Hispanic":677,"county":"Isle of Wight County","state_fips":"51"}],"2020":[{"year":2020,"NHWhite":26058,"Black":8373,"American Indian/Alaska Native":62,"Asian":338,"Pacific Islander":9,"NHOther":0,"NHMulti":965,"Hispanic":1302,"county":"Isle of Wight County","state_fips":"51"}]},"James City County":{"2010":[{"year":2010,"NHWhite":50469,"Black":8536,"American Indian/Alaska Native":71,"Asian":1464,"Pacific Islander":97,"NHOther":122,"NHMulti":974,"Hispanic":2653,"county":"James City County","state_fips":"51"}],"2020":[{"year":2020,"NHWhite":56879,"Black":9524,"American Indian/Alaska Native":26,"Asian":2160,"Pacific Islander":12,"NHOther":411,"NHMulti":2533,"Hispanic":4487,"county":"James City County","state_fips":"51"}]},"King and Queen County":{"2010":[{"year":2010,"NHWhite":4515,"Black":2199,"American Indian/Alaska Native":50,"Asian":0,"Pacific Islander":0,"NHOther":0,"NHMulti":0,"Hispanic":162,"county":"King and Queen County","state_fips":"51"}],"2020":[{"year":2020,"NHWhite":4628,"Black":1965,"American Indian/Alaska Native":7,"Asian":0,"Pacific Islander":0,"NHOther":0,"NHMulti":176,"Hispanic":235,"county":"King and Queen County","state_fips":"51"}]},"King George County":{"2010":[{"year":2010,"NHWhite":17080,"Black":3867,"American Indian/Alaska Native":92,"Asian":205,"Pacific Islander":11,"NHOther":52,"NHMulti":663,"Hispanic":824,"county":"King George County","state_fips":"51"}],"2020":[{"year":2020,"NHWhite":19381,"Black":4397,"American Indian/Alaska Native":27,"Asian":273,"Pacific Islander":0,"NHOther":75,"NHMulti":1031,"Hispanic":1495,"county":"King George County","state_fips":"51"}]},"King William County":{"2010":[{"year":2010,"NHWhite":11751,"Black":2907,"American Indian/Alaska Native":287,"Asian":13,"Pacific Islander":0,"NHOther":0,"NHMulti":207,"Hispanic":344,"county":"King William County","state_fips":"51"}],"2020":[{"year":2020,"NHWhite":13084,"Black":2558,"American Indian/Alaska Native":121,"Asian":237,"Pacific Islander":0,"NHOther":9,"NHMulti":518,"Hispanic":458,"county":"King William County","state_fips":"51"}]},"Lancaster County":{"2010":[{"year":2010,"NHWhite":8020,"Black":3297,"American Indian/Alaska Native":0,"Asian":34,"Pacific Islander":0,"NHOther":0,"NHMulti":57,"Hispanic":70,"county":"Lancaster County","state_fips":"51"}],"2020":[{"year":2020,"NHWhite":7187,"Black":2966,"American Indian/Alaska Native":0,"Asian":111,"Pacific Islander":0,"NHOther":0,"NHMulti":328,"Hispanic":94,"county":"Lancaster County","state_fips":"51"}]},"Lee County":{"2010":[{"year":2010,"NHWhite":23810,"Black":943,"American Indian/Alaska Native":87,"Asian":158,"Pacific Islander":42,"NHOther":6,"NHMulti":15,"Hispanic":373,"county":"Lee County","state_fips":"51"}],"2020":[{"year":2020,"NHWhite":22068,"Black":876,"American Indian/Alaska Native":45,"Asian":60,"Pacific Islander":0,"NHOther":0,"NHMulti":189,"Hispanic":485,"county":"Lee County","state_fips":"51"}]},"Lexington city":{"2010":[{"year":2010,"NHWhite":5549,"Black":463,"American Indian/Alaska Native":0,"Asian":210,"Pacific Islander":10,"NHOther":88,"NHMulti":205,"Hispanic":465,"county":"Lexington city","state_fips":"51"}],"2020":[{"year":2020,"NHWhite":5722,"Black":452,"American Indian/Alaska Native":0,"Asian":362,"Pacific Islander":0,"NHOther":15,"NHMulti":253,"Hispanic":401,"county":"Lexington city","state_fips":"51"}]},"Loudoun County":{"2010":[{"year":2010,"NHWhite":187588,"Black":20321,"American Indian/Alaska Native":297,"Asian":40793,"Pacific Islander":174,"NHOther":730,"NHMulti":7605,"Hispanic":34145,"county":"Loudoun County","state_fips":"51"}],"2020":[{"year":2020,"NHWhite":223329,"Black":30117,"American Indian/Alaska Native":847,"Asian":77332,"Pacific Islander":288,"NHOther":2303,"NHMulti":15916,"Hispanic":55180,"county":"Loudoun County","state_fips":"51"}]},"Louisa County":{"2010":[{"year":2010,"NHWhite":24867,"Black":5882,"American Indian/Alaska Native":139,"Asian":195,"Pacific Islander":0,"NHOther":18,"NHMulti":431,"Hispanic":716,"county":"Louisa County","state_fips":"51"}],"2020":[{"year":2020,"NHWhite":28620,"Black":5163,"American Indian/Alaska Native":48,"Asian":196,"Pacific Islander":0,"NHOther":8,"NHMulti":1479,"Hispanic":1140,"county":"Louisa County","state_fips":"51"}]},"Lunenburg County":{"2010":[{"year":2010,"NHWhite":7711,"Black":4754,"American Indian/Alaska Native":0,"Asian":0,"Pacific Islander":11,"NHOther":0,"NHMulti":87,"Hispanic":405,"county":"Lunenburg County","state_fips":"51"}],"2020":[{"year":2020,"NHWhite":7259,"Black":4137,"American Indian/Alaska Native":2,"Asian":61,"Pacific Islander":0,"NHOther":0,"NHMulti":198,"Hispanic":637,"county":"Lunenburg County","state_fips":"51"}]},"Lynchburg city":{"2010":[{"year":2010,"NHWhite":46912,"Black":21376,"American Indian/Alaska Native":107,"Asian":1702,"Pacific Islander":11,"NHOther":74,"NHMulti":1457,"Hispanic":2087,"county":"Lynchburg city","state_fips":"51"}],"2020":[{"year":2020,"NHWhite":50382,"Black":22834,"American Indian/Alaska Native":163,"Asian":1934,"Pacific Islander":47,"NHOther":189,"NHMulti":1891,"Hispanic":3530,"county":"Lynchburg city","state_fips":"51"}]},"Madison County":{"2010":[{"year":2010,"NHWhite":11376,"Black":1408,"American Indian/Alaska Native":55,"Asian":69,"Pacific Islander":13,"NHOther":72,"NHMulti":60,"Hispanic":289,"county":"Madison County","state_fips":"51"}],"2020":[{"year":2020,"NHWhite":11191,"Black":1203,"American Indian/Alaska Native":0,"Asian":129,"Pacific Islander":0,"NHOther":0,"NHMulti":296,"Hispanic":389,"county":"Madison County","state_fips":"51"}]},"Manassas city":{"2010":[{"year":2010,"NHWhite":18361,"Black":4481,"American Indian/Alaska Native":24,"Asian":1394,"Pacific Islander":0,"NHOther":71,"NHMulti":1049,"Hispanic":10687,"county":"Manassas city","state_fips":"51"}],"2020":[{"year":2020,"NHWhite":16248,"Black":5169,"American Indian/Alaska Native":139,"Asian":2285,"Pacific Islander":0,"NHOther":288,"NHMulti":1656,"Hispanic":15253,"county":"Manassas city","state_fips":"51"}]},"Manassas Park city":{"2010":[{"year":2010,"NHWhite":5820,"Black":1602,"American Indian/Alaska Native":8,"Asian":988,"Pacific Islander":0,"NHOther":13,"NHMulti":424,"Hispanic":4340,"county":"Manassas Park city","state_fips":"51"}],"2020":[{"year":2020,"NHWhite":5704,"Black":2452,"American Indian/Alaska Native":0,"Asian":1982,"Pacific Islander":0,"NHOther":23,"NHMulti":355,"Hispanic":7032,"county":"Manassas Park city","state_fips":"51"}]},"Martinsville city":{"2010":[{"year":2010,"NHWhite":6964,"Black":6262,"American Indian/Alaska Native":81,"Asian":80,"Pacific Islander":0,"NHOther":58,"NHMulti":67,"Hispanic":517,"county":"Martinsville city","state_fips":"51"}],"2020":[{"year":2020,"NHWhite":5498,"Black":5736,"American Indian/Alaska Native":43,"Asian":145,"Pacific Islander":13,"NHOther":92,"NHMulti":339,"Hispanic":780,"county":"Martinsville city","state_fips":"51"}]},"Mathews County":{"2010":[{"year":2010,"NHWhite":7819,"Black":889,"American Indian/Alaska Native":74,"Asian":0,"Pacific Islander":0,"NHOther":39,"NHMulti":75,"Hispanic":108,"county":"Mathews County","state_fips":"51"}],"2020":[{"year":2020,"NHWhite":7499,"Black":714,"American Indian/Alaska Native":0,"Asian":42,"Pacific Islander":0,"NHOther":0,"NHMulti":266,"Hispanic":239,"county":"Mathews County","state_fips":"51"}]},"Mecklenburg County":{"2010":[{"year":2010,"NHWhite":19286,"Black":12252,"American Indian/Alaska Native":0,"Asian":214,"Pacific Islander":18,"NHOther":12,"NHMulti":219,"Hispanic":773,"county":"Mecklenburg County","state_fips":"51"}],"2020":[{"year":2020,"NHWhite":18497,"Black":10510,"American Indian/Alaska Native":157,"Asian":289,"Pacific Islander":4,"NHOther":0,"NHMulti":356,"Hispanic":913,"county":"Mecklenburg County","state_fips":"51"}]},"Middlesex County":{"2010":[{"year":2010,"NHWhite":8495,"Black":2086,"American Indian/Alaska Native":21,"Asian":0,"Pacific Islander":0,"NHOther":37,"NHMulti":65,"Hispanic":127,"county":"Middlesex County","state_fips":"51"}],"2020":[{"year":2020,"NHWhite":8271,"Black":1583,"American Indian/Alaska Native":41,"Asian":72,"Pacific Islander":18,"NHOther":203,"NHMulti":281,"Hispanic":173,"county":"Middlesex County","state_fips":"51"}]},"Montgomery County":{"2010":[{"year":2010,"NHWhite":79864,"Black":3573,"American Indian/Alaska Native":86,"Asian":5168,"Pacific Islander":13,"NHOther":233,"NHMulti":1217,"Hispanic":2373,"county":"Montgomery County","state_fips":"51"}],"2020":[{"year":2020,"NHWhite":82127,"Black":4022,"American Indian/Alaska Native":368,"Asian":6527,"Pacific Islander":27,"NHOther":350,"NHMulti":1777,"Hispanic":3297,"county":"Montgomery County","state_fips":"51"}]},"Nelson County":{"2010":[{"year":2010,"NHWhite":12301,"Black":2062,"American Indian/Alaska Native":0,"Asian":28,"Pacific Islander":0,"NHOther":0,"NHMulti":199,"Hispanic":399,"county":"Nelson County","state_fips":"51"}],"2020":[{"year":2020,"NHWhite":12035,"Black":1915,"American Indian/Alaska Native":0,"Asian":45,"Pacific Islander":0,"NHOther":46,"NHMulti":126,"Hispanic":645,"county":"Nelson County","state_fips":"51"}]},"New Kent County":{"2010":[{"year":2010,"NHWhite":14186,"Black":2838,"American Indian/Alaska Native":242,"Asian":132,"Pacific Islander":0,"NHOther":20,"NHMulti":90,"Hispanic":147,"county":"New Kent County","state_fips":"51"}],"2020":[{"year":2020,"NHWhite":17481,"Black":2864,"American Indian/Alaska Native":227,"Asian":254,"Pacific Islander":0,"NHOther":0,"NHMulti":695,"Hispanic":789,"county":"New Kent County","state_fips":"51"}]},"Newport News city":{"2010":[{"year":2010,"NHWhite":85471,"Black":72115,"American Indian/Alaska Native":526,"Asian":4945,"Pacific Islander":326,"NHOther":565,"NHMulti":5450,"Hispanic":12424,"county":"Newport News city","state_fips":"51"}],"2020":[{"year":2020,"NHWhite":75587,"Black":71917,"American Indian/Alaska Native":340,"Asian":5715,"Pacific Islander":155,"NHOther":956,"NHMulti":8096,"Hispanic":16816,"county":"Newport News city","state_fips":"51"}]},"Norfolk city":{"2010":[{"year":2010,"NHWhite":107951,"Black":104215,"American Indian/Alaska Native":821,"Asian":7868,"Pacific Islander":413,"NHOther":716,"NHMulti":5103,"Hispanic":15056,"county":"Norfolk city","state_fips":"51"}],"2020":[{"year":2020,"NHWhite":105247,"Black":97851,"American Indian/Alaska Native":518,"Asian":8726,"Pacific Islander":106,"NHOther":849,"NHMulti":10551,"Hispanic":20452,"county":"Norfolk city","state_fips":"51"}]},"Northampton County":{"2010":[{"year":2010,"NHWhite":6849,"Black":4826,"American Indian/Alaska Native":4,"Asian":102,"Pacific Islander":0,"NHOther":0,"NHMulti":50,"Hispanic":741,"county":"Northampton County","state_fips":"51"}],"2020":[{"year":2020,"NHWhite":6464,"Black":3906,"American Indian/Alaska Native":2,"Asian":130,"Pacific Islander":0,"NHOther":0,"NHMulti":277,"Hispanic":1047,"county":"Northampton County","state_fips":"51"}]},"Northumberland County":{"2010":[{"year":2010,"NHWhite":8763,"Black":3416,"American Indian/Alaska Native":13,"Asian":101,"Pacific Islander":0,"NHOther":0,"NHMulti":16,"Hispanic":110,"county":"Northumberland County","state_fips":"51"}],"2020":[{"year":2020,"NHWhite":8422,"Black":3208,"American Indian/Alaska Native":0,"Asian":17,"Pacific Islander":0,"NHOther":0,"NHMulti":333,"Hispanic":171,"county":"Northumberland County","state_fips":"51"}]},"Norton city":{"2010":[{"year":2010,"NHWhite":3611,"Black":208,"American Indian/Alaska Native":0,"Asian":15,"Pacific Islander":0,"NHOther":0,"NHMulti":52,"Hispanic":0,"county":"Norton city","state_fips":"51"}],"2020":[{"year":2020,"NHWhite":3711,"Black":204,"American Indian/Alaska Native":0,"Asian":0,"Pacific Islander":0,"NHOther":0,"NHMulti":54,"Hispanic":0,"county":"Norton city","state_fips":"51"}]},"Nottoway County":{"2010":[{"year":2010,"NHWhite":8703,"Black":6238,"American Indian/Alaska Native":190,"Asian":13,"Pacific Islander":19,"NHOther":71,"NHMulti":70,"Hispanic":515,"county":"Nottoway County","state_fips":"51"}],"2020":[{"year":2020,"NHWhite":8304,"Black":6193,"American Indian/Alaska Native":7,"Asian":63,"Pacific Islander":0,"NHOther":0,"NHMulti":72,"Hispanic":699,"county":"Nottoway County","state_fips":"51"}]},"Orange County":{"2010":[{"year":2010,"NHWhite":26658,"Black":4169,"American Indian/Alaska Native":10,"Asian":211,"Pacific Islander":0,"NHOther":0,"NHMulti":586,"Hispanic":1096,"county":"Orange County","state_fips":"51"}],"2020":[{"year":2020,"NHWhite":28366,"Black":4643,"American Indian/Alaska Native":82,"Asian":517,"Pacific Islander":0,"NHOther":22,"NHMulti":955,"Hispanic":1916,"county":"Orange County","state_fips":"51"}]},"Page County":{"2010":[{"year":2010,"NHWhite":22958,"Black":443,"American Indian/Alaska Native":32,"Asian":119,"Pacific Islander":0,"NHOther":0,"NHMulti":185,"Hispanic":379,"county":"Page County","state_fips":"51"}],"2020":[{"year":2020,"NHWhite":22286,"Black":282,"American Indian/Alaska Native":39,"Asian":130,"Pacific Islander":0,"NHOther":67,"NHMulti":555,"Hispanic":503,"county":"Page County","state_fips":"51"}]},"Patrick County":{"2010":[{"year":2010,"NHWhite":16833,"Black":1149,"American Indian/Alaska Native":87,"Asian":36,"Pacific Islander":0,"NHOther":0,"NHMulti":126,"Hispanic":412,"county":"Patrick County","state_fips":"51"}],"2020":[{"year":2020,"NHWhite":15845,"Black":959,"American Indian/Alaska Native":17,"Asian":76,"Pacific Islander":0,"NHOther":59,"NHMulti":153,"Hispanic":551,"county":"Patrick County","state_fips":"51"}]},"Petersburg city":{"2010":[{"year":2010,"NHWhite":4942,"Black":25564,"American Indian/Alaska Native":39,"Asian":171,"Pacific Islander":110,"NHOther":61,"NHMulti":282,"Hispanic":1134,"county":"Petersburg city","state_fips":"51"}],"2020":[{"year":2020,"NHWhite":4610,"Black":23479,"American Indian/Alaska Native":134,"Asian":307,"Pacific Islander":9,"NHOther":52,"NHMulti":684,"Hispanic":1516,"county":"Petersburg city","state_fips":"51"}]},"Pittsylvania County":{"2010":[{"year":2010,"NHWhite":46886,"Black":14169,"American Indian/Alaska Native":8,"Asian":164,"Pacific Islander":15,"NHOther":97,"NHMulti":536,"Hispanic":1272,"county":"Pittsylvania County","state_fips":"51"}],"2020":[{"year":2020,"NHWhite":44975,"Black":12248,"American Indian/Alaska Native":26,"Asian":262,"Pacific Islander":0,"NHOther":29,"NHMulti":1673,"Hispanic":1654,"county":"Pittsylvania County","state_fips":"51"}]},"Poquoson city":{"2010":[{"year":2010,"NHWhite":11418,"Black":56,"American Indian/Alaska Native":0,"Asian":328,"Pacific Islander":0,"NHOther":0,"NHMulti":112,"Hispanic":185,"county":"Poquoson city","state_fips":"51"}],"2020":[{"year":2020,"NHWhite":10976,"Black":182,"American Indian/Alaska Native":12,"Asian":270,"Pacific Islander":0,"NHOther":0,"NHMulti":329,"Hispanic":352,"county":"Poquoson city","state_fips":"51"}]},"Portsmouth city":{"2010":[{"year":2010,"NHWhite":39804,"Black":50214,"American Indian/Alaska Native":264,"Asian":1046,"Pacific Islander":129,"NHOther":69,"NHMulti":2390,"Hispanic":2869,"county":"Portsmouth city","state_fips":"51"}],"2020":[{"year":2020,"NHWhite":35156,"Black":49340,"American Indian/Alaska Native":320,"Asian":1482,"Pacific Islander":309,"NHOther":361,"NHMulti":3566,"Hispanic":4427,"county":"Portsmouth city","state_fips":"51"}]},"Powhatan County":{"2010":[{"year":2010,"NHWhite":21569,"Black":5338,"American Indian/Alaska Native":0,"Asian":144,"Pacific Islander":0,"NHOther":6,"NHMulti":226,"Hispanic":475,"county":"Powhatan County","state_fips":"51"}],"2020":[{"year":2020,"NHWhite":24899,"Black":2763,"American Indian/Alaska Native":25,"Asian":49,"Pacific Islander":20,"NHOther":77,"NHMulti":756,"Hispanic":664,"county":"Powhatan County","state_fips":"51"}]},"Prince Edward County":{"2010":[{"year":2010,"NHWhite":14106,"Black":7988,"American Indian/Alaska Native":59,"Asian":62,"Pacific Islander":6,"NHOther":0,"NHMulti":289,"Hispanic":213,"county":"Prince Edward County","state_fips":"51"}],"2020":[{"year":2020,"NHWhite":13967,"Black":7217,"American Indian/Alaska Native":79,"Asian":149,"Pacific Islander":0,"NHOther":11,"NHMulti":771,"Hispanic":698,"county":"Prince Edward County","state_fips":"51"}]},"Prince George County":{"2010":[{"year":2010,"NHWhite":20435,"Black":11338,"American Indian/Alaska Native":243,"Asian":507,"Pacific Islander":49,"NHOther":44,"NHMulti":472,"Hispanic":2041,"county":"Prince George County","state_fips":"51"}],"2020":[{"year":2020,"NHWhite":20856,"Black":11678,"American Indian/Alaska Native":174,"Asian":577,"Pacific Islander":157,"NHOther":156,"NHMulti":1467,"Hispanic":3227,"county":"Prince George County","state_fips":"51"}]},"Prince William County":{"2010":[{"year":2010,"NHWhite":189455,"Black":72489,"American Indian/Alaska Native":875,"Asian":27691,"Pacific Islander":447,"NHOther":1708,"NHMulti":10944,"Hispanic":75806,"county":"Prince William County","state_fips":"51"}],"2020":[{"year":2020,"NHWhite":194705,"Black":95384,"American Indian/Alaska Native":1103,"Asian":43618,"Pacific Islander":317,"NHOther":1840,"NHMulti":18160,"Hispanic":111707,"county":"Prince William County","state_fips":"51"}]},"Pulaski County":{"2010":[{"year":2010,"NHWhite":31928,"Black":1919,"American Indian/Alaska Native":19,"Asian":174,"Pacific Islander":0,"NHOther":151,"NHMulti":287,"Hispanic":485,"county":"Pulaski County","state_fips":"51"}],"2020":[{"year":2020,"NHWhite":30926,"Black":1538,"American Indian/Alaska Native":0,"Asian":254,"Pacific Islander":80,"NHOther":41,"NHMulti":653,"Hispanic":621,"county":"Pulaski County","state_fips":"51"}]},"Radford city":{"2010":[{"year":2010,"NHWhite":14112,"Black":1301,"American Indian/Alaska Native":0,"Asian":265,"Pacific Islander":18,"NHOther":13,"NHMulti":244,"Hispanic":365,"county":"Radford city","state_fips":"51"}],"2020":[{"year":2020,"NHWhite":14827,"Black":1727,"American Indian/Alaska Native":29,"Asian":279,"Pacific Islander":4,"NHOther":45,"NHMulti":388,"Hispanic":534,"county":"Radford city","state_fips":"51"}]},"Rappahannock County":{"2010":[{"year":2010,"NHWhite":6650,"Black":449,"American Indian/Alaska Native":31,"Asian":12,"Pacific Islander":0,"NHOther":21,"NHMulti":110,"Hispanic":103,"county":"Rappahannock County","state_fips":"51"}],"2020":[{"year":2020,"NHWhite":6497,"Black":334,"American Indian/Alaska Native":38,"Asian":18,"Pacific Islander":0,"NHOther":17,"NHMulti":167,"Hispanic":289,"county":"Rappahannock County","state_fips":"51"}]},"Richmond city":{"2010":[{"year":2010,"NHWhite":77619,"Black":102681,"American Indian/Alaska Native":325,"Asian":4485,"Pacific Islander":38,"NHOther":547,"NHMulti":4914,"Hispanic":11219,"county":"Richmond city","state_fips":"51"}],"2020":[{"year":2020,"NHWhite":94400,"Black":104961,"American Indian/Alaska Native":277,"Asian":4733,"Pacific Islander":8,"NHOther":687,"NHMulti":7947,"Hispanic":16220,"county":"Richmond city","state_fips":"51"}]},"Richmond County":{"2010":[{"year":2010,"NHWhite":5828,"Black":2898,"American Indian/Alaska Native":62,"Asian":23,"Pacific Islander":0,"NHOther":0,"NHMulti":91,"Hispanic":426,"county":"Richmond County","state_fips":"51"}],"2020":[{"year":2020,"NHWhite":5423,"Black":2420,"American Indian/Alaska Native":19,"Asian":28,"Pacific Islander":0,"NHOther":0,"NHMulti":414,"Hispanic":647,"county":"Richmond County","state_fips":"51"}]},"Roanoke city":{"2010":[{"year":2010,"NHWhite":60310,"Black":26860,"American Indian/Alaska Native":287,"Asian":1499,"Pacific Islander":0,"NHOther":217,"NHMulti":2177,"Hispanic":4443,"county":"Roanoke city","state_fips":"51"}],"2020":[{"year":2020,"NHWhite":57543,"Black":28306,"American Indian/Alaska Native":206,"Asian":3211,"Pacific Islander":48,"NHOther":197,"NHMulti":3265,"Hispanic":6346,"county":"Roanoke city","state_fips":"51"}]},"Roanoke County":{"2010":[{"year":2010,"NHWhite":81621,"Black":4552,"American Indian/Alaska Native":145,"Asian":2295,"Pacific Islander":7,"NHOther":151,"NHMulti":888,"Hispanic":1924,"county":"Roanoke County","state_fips":"51"}],"2020":[{"year":2020,"NHWhite":80431,"Black":5549,"American Indian/Alaska Native":175,"Asian":3153,"Pacific Islander":33,"NHOther":51,"NHMulti":1714,"Hispanic":2997,"county":"Roanoke County","state_fips":"51"}]},"Rockbridge County":{"2010":[{"year":2010,"NHWhite":21475,"Black":470,"American Indian/Alaska Native":29,"Asian":17,"Pacific Islander":85,"NHOther":3,"NHMulti":104,"Hispanic":34,"county":"Rockbridge County","state_fips":"51"}],"2020":[{"year":2020,"NHWhite":20884,"Black":661,"American Indian/Alaska Native":88,"Asian":248,"Pacific Islander":0,"NHOther":29,"NHMulti":362,"Hispanic":456,"county":"Rockbridge County","state_fips":"51"}]},"Rockingham County":{"2010":[{"year":2010,"NHWhite":68705,"Black":1362,"American Indian/Alaska Native":122,"Asian":449,"Pacific Islander":17,"NHOther":0,"NHMulti":506,"Hispanic":3761,"county":"Rockingham County","state_fips":"51"}],"2020":[{"year":2020,"NHWhite":71485,"Black":1840,"American Indian/Alaska Native":63,"Asian":575,"Pacific Islander":59,"NHOther":175,"NHMulti":1109,"Hispanic":5832,"county":"Rockingham County","state_fips":"51"}]},"Russell County":{"2010":[{"year":2010,"NHWhite":28110,"Black":365,"American Indian/Alaska Native":32,"Asian":80,"Pacific Islander":0,"NHOther":0,"NHMulti":227,"Hispanic":28,"county":"Russell County","state_fips":"51"}],"2020":[{"year":2020,"NHWhite":25998,"Black":246,"American Indian/Alaska Native":67,"Asian":0,"Pacific Islander":0,"NHOther":0,"NHMulti":429,"Hispanic":197,"county":"Russell County","state_fips":"51"}]},"Salem city":{"2010":[{"year":2010,"NHWhite":21768,"Black":1632,"American Indian/Alaska Native":26,"Asian":262,"Pacific Islander":0,"NHOther":0,"NHMulti":424,"Hispanic":529,"county":"Salem city","state_fips":"51"}],"2020":[{"year":2020,"NHWhite":21390,"Black":1653,"American Indian/Alaska Native":11,"Asian":458,"Pacific Islander":28,"NHOther":232,"NHMulti":650,"Hispanic":868,"county":"Salem city","state_fips":"51"}]},"Scott County":{"2010":[{"year":2010,"NHWhite":22646,"Black":136,"American Indian/Alaska Native":13,"Asian":15,"Pacific Islander":0,"NHOther":0,"NHMulti":231,"Hispanic":193,"county":"Scott County","state_fips":"51"}],"2020":[{"year":2020,"NHWhite":21009,"Black":147,"American Indian/Alaska Native":63,"Asian":17,"Pacific Islander":0,"NHOther":0,"NHMulti":227,"Hispanic":298,"county":"Scott County","state_fips":"51"}]},"Shenandoah County":{"2010":[{"year":2010,"NHWhite":37735,"Black":789,"American Indian/Alaska Native":118,"Asian":234,"Pacific Islander":7,"NHOther":4,"NHMulti":251,"Hispanic":2330,"county":"Shenandoah County","state_fips":"51"}],"2020":[{"year":2020,"NHWhite":37857,"Black":696,"American Indian/Alaska Native":51,"Asian":390,"Pacific Islander":0,"NHOther":73,"NHMulti":1166,"Hispanic":3208,"county":"Shenandoah County","state_fips":"51"}]},"Smyth County":{"2010":[{"year":2010,"NHWhite":30892,"Black":568,"American Indian/Alaska Native":81,"Asian":42,"Pacific Islander":0,"NHOther":7,"NHMulti":326,"Hispanic":467,"county":"Smyth County","state_fips":"51"}],"2020":[{"year":2020,"NHWhite":28703,"Black":674,"American Indian/Alaska Native":94,"Asian":190,"Pacific Islander":46,"NHOther":0,"NHMulti":193,"Hispanic":639,"county":"Smyth County","state_fips":"51"}]},"Southampton County":{"2010":[{"year":2010,"NHWhite":11005,"Black":7060,"American Indian/Alaska Native":72,"Asian":50,"Pacific Islander":0,"NHOther":0,"NHMulti":208,"Hispanic":98,"county":"Southampton County","state_fips":"51"}],"2020":[{"year":2020,"NHWhite":10856,"Black":5875,"American Indian/Alaska Native":64,"Asian":65,"Pacific Islander":0,"NHOther":32,"NHMulti":603,"Hispanic":334,"county":"Southampton County","state_fips":"51"}]},"Spotsylvania County":{"2010":[{"year":2010,"NHWhite":87595,"Black":18136,"American Indian/Alaska Native":234,"Asian":2884,"Pacific Islander":144,"NHOther":296,"NHMulti":2175,"Hispanic":8748,"county":"Spotsylvania County","state_fips":"51"}],"2020":[{"year":2020,"NHWhite":90587,"Black":21421,"American Indian/Alaska Native":232,"Asian":3351,"Pacific Islander":88,"NHOther":343,"NHMulti":4982,"Hispanic":13679,"county":"Spotsylvania County","state_fips":"51"}]},"Stafford County":{"2010":[{"year":2010,"NHWhite":85747,"Black":20750,"American Indian/Alaska Native":538,"Asian":3404,"Pacific Islander":44,"NHOther":381,"NHMulti":2813,"Hispanic":10910,"county":"Stafford County","state_fips":"51"}],"2020":[{"year":2020,"NHWhite":89842,"Black":26283,"American Indian/Alaska Native":404,"Asian":4883,"Pacific Islander":81,"NHOther":430,"NHMulti":8108,"Hispanic":20154,"county":"Stafford County","state_fips":"51"}]},"Statewide":{"2010":[{"year":2010,"NHWhite":5151070,"Black":1510543,"American Indian/Alaska Native":18555,"Asian":413524,"Pacific Islander":5199,"NHOther":19301,"NHMulti":148596,"Hispanic":574966,"county":"Statewide","state_fips":"51"}],"2020":[{"year":2020,"NHWhite":5209336,"Black":1590974,"American Indian/Alaska Native":16856,"Asian":564706,"Pacific Islander":4680,"NHOther":26839,"NHMulti":285197,"Hispanic":810770,"county":"Statewide","state_fips":"51"}]},"Staunton city":{"2010":[{"year":2010,"NHWhite":19728,"Black":2780,"American Indian/Alaska Native":114,"Asian":177,"Pacific Islander":0,"NHOther":20,"NHMulti":483,"Hispanic":504,"county":"Staunton city","state_fips":"51"}],"2020":[{"year":2020,"NHWhite":19860,"Black":2639,"American Indian/Alaska Native":95,"Asian":355,"Pacific Islander":27,"NHOther":11,"NHMulti":836,"Hispanic":837,"county":"Staunton city","state_fips":"51"}]},"Suffolk city":{"2010":[{"year":2010,"NHWhite":42835,"Black":34225,"American Indian/Alaska Native":139,"Asian":1317,"Pacific Islander":5,"NHOther":182,"NHMulti":1591,"Hispanic":2250,"county":"Suffolk city","state_fips":"51"}],"2020":[{"year":2020,"NHWhite":44706,"Black":37218,"American Indian/Alaska Native":127,"Asian":1892,"Pacific Islander":9,"NHOther":204,"NHMulti":3129,"Hispanic":4098,"county":"Suffolk city","state_fips":"51"}]},"Surry County":{"2010":[{"year":2010,"NHWhite":3524,"Black":3380,"American Indian/Alaska Native":0,"Asian":0,"Pacific Islander":0,"NHOther":0,"NHMulti":43,"Hispanic":92,"county":"Surry County","state_fips":"51"}],"2020":[{"year":2020,"NHWhite":3412,"Black":2786,"American Indian/Alaska Native":3,"Asian":0,"Pacific Islander":0,"NHOther":0,"NHMulti":89,"Hispanic":169,"county":"Surry County","state_fips":"51"}]},"Sussex County":{"2010":[{"year":2010,"NHWhite":4623,"Black":7354,"American Indian/Alaska Native":19,"Asian":0,"Pacific Islander":0,"NHOther":0,"NHMulti":2,"Hispanic":169,"county":"Sussex County","state_fips":"51"}],"2020":[{"year":2020,"NHWhite":4309,"Black":6217,"American Indian/Alaska Native":0,"Asian":63,"Pacific Islander":0,"NHOther":9,"NHMulti":248,"Hispanic":356,"county":"Sussex County","state_fips":"51"}]},"Tazewell County":{"2010":[{"year":2010,"NHWhite":42509,"Black":1234,"American Indian/Alaska Native":83,"Asian":259,"Pacific Islander":0,"NHOther":97,"NHMulti":464,"Hispanic":60,"county":"Tazewell County","state_fips":"51"}],"2020":[{"year":2020,"NHWhite":38609,"Black":1317,"American Indian/Alaska Native":63,"Asian":282,"Pacific Islander":25,"NHOther":0,"NHMulti":464,"Hispanic":441,"county":"Tazewell County","state_fips":"51"}]},"Virginia Beach city":{"2010":[{"year":2010,"NHWhite":284947,"Black":81633,"American Indian/Alaska Native":724,"Asian":25880,"Pacific Islander":515,"NHOther":708,"NHMulti":14413,"Hispanic":27176,"county":"Virginia Beach city","state_fips":"51"}],"2020":[{"year":2020,"NHWhite":275271,"Black":82565,"American Indian/Alaska Native":829,"Asian":31447,"Pacific Islander":387,"NHOther":1118,"NHMulti":21371,"Hispanic":37894,"county":"Virginia Beach city","state_fips":"51"}]},"Warren County":{"2010":[{"year":2010,"NHWhite":33032,"Black":1491,"American Indian/Alaska Native":119,"Asian":242,"Pacific Islander":71,"NHOther":29,"NHMulti":781,"Hispanic":1279,"county":"Warren County","state_fips":"51"}],"2020":[{"year":2020,"NHWhite":34416,"Black":1612,"American Indian/Alaska Native":83,"Asian":461,"Pacific Islander":0,"NHOther":78,"NHMulti":1277,"Hispanic":1961,"county":"Warren County","state_fips":"51"}]},"Washington County":{"2010":[{"year":2010,"NHWhite":52364,"Black":601,"American Indian/Alaska Native":64,"Asian":179,"Pacific Islander":0,"NHOther":6,"NHMulti":413,"Hispanic":695,"county":"Washington County","state_fips":"51"}],"2020":[{"year":2020,"NHWhite":51419,"Black":697,"American Indian/Alaska Native":26,"Asian":296,"Pacific Islander":6,"NHOther":60,"NHMulti":677,"Hispanic":824,"county":"Washington County","state_fips":"51"}]},"Waynesboro city":{"2010":[{"year":2010,"NHWhite":16836,"Black":1868,"American Indian/Alaska Native":108,"Asian":200,"Pacific Islander":0,"NHOther":0,"NHMulti":644,"Hispanic":1229,"county":"Waynesboro city","state_fips":"51"}],"2020":[{"year":2020,"NHWhite":16614,"Black":2667,"American Indian/Alaska Native":134,"Asian":378,"Pacific Islander":95,"NHOther":0,"NHMulti":502,"Hispanic":1910,"county":"Waynesboro city","state_fips":"51"}]},"Westmoreland County":{"2010":[{"year":2010,"NHWhite":10977,"Black":4902,"American Indian/Alaska Native":0,"Asian":95,"Pacific Islander":0,"NHOther":14,"NHMulti":336,"Hispanic":913,"county":"Westmoreland County","state_fips":"51"}],"2020":[{"year":2020,"NHWhite":11401,"Black":4470,"American Indian/Alaska Native":49,"Asian":126,"Pacific Islander":2,"NHOther":187,"NHMulti":485,"Hispanic":1153,"county":"Westmoreland County","state_fips":"51"}]},"Williamsburg city":{"2010":[{"year":2010,"NHWhite":9665,"Black":1801,"American Indian/Alaska Native":0,"Asian":678,"Pacific Islander":0,"NHOther":0,"NHMulti":463,"Hispanic":814,"county":"Williamsburg city","state_fips":"51"}],"2020":[{"year":2020,"NHWhite":10214,"Black":2285,"American Indian/Alaska Native":36,"Asian":997,"Pacific Islander":0,"NHOther":24,"NHMulti":393,"Hispanic":1085,"county":"Williamsburg city","state_fips":"51"}]},"Winchester city":{"2010":[{"year":2010,"NHWhite":18489,"Black":2880,"American Indian/Alaska Native":26,"Asian":618,"Pacific Islander":13,"NHOther":60,"NHMulti":389,"Hispanic":3478,"county":"Winchester city","state_fips":"51"}],"2020":[{"year":2020,"NHWhite":18102,"Black":2777,"American Indian/Alaska Native":53,"Asian":532,"Pacific Islander":0,"NHOther":228,"NHMulti":1240,"Hispanic":4980,"county":"Winchester city","state_fips":"51"}]},"Wise County":{"2010":[{"year":2010,"NHWhite":38378,"Black":2140,"American Indian/Alaska Native":54,"Asian":133,"Pacific Islander":26,"NHOther":48,"NHMulti":256,"Hispanic":461,"county":"Wise County","state_fips":"51"}],"2020":[{"year":2020,"NHWhite":34733,"Black":2106,"American Indian/Alaska Native":62,"Asian":187,"Pacific Islander":14,"NHOther":56,"NHMulti":391,"Hispanic":483,"county":"Wise County","state_fips":"51"}]},"Wythe County":{"2010":[{"year":2010,"NHWhite":27423,"Black":1140,"American Indian/Alaska Native":8,"Asian":64,"Pacific Islander":0,"NHOther":32,"NHMulti":55,"Hispanic":283,"county":"Wythe County","state_fips":"51"}],"2020":[{"year":2020,"NHWhite":26935,"Black":585,"American Indian/Alaska Native":45,"Asian":283,"Pacific Islander":0,"NHOther":0,"NHMulti":511,"Hispanic":366,"county":"Wythe County","state_fips":"51"}]},"York County":{"2010":[{"year":2010,"NHWhite":48681,"Black":8766,"American Indian/Alaska Native":106,"Asian":2791,"Pacific Islander":155,"NHOther":61,"NHMulti":1460,"Hispanic":2826,"county":"York County","state_fips":"51"}],"2020":[{"year":2020,"NHWhite":47836,"Black":8916,"American Indian/Alaska Native":98,"Asian":3841,"Pacific Islander":171,"NHOther":194,"NHMulti":2715,"Hispanic":4618,"county":"York County","state_fips":"51"}]}}
