{"Statewide":[12,46.7,15.2,11.6,5.3,9.1],"Alcona County, Michigan":[13.8,51.9,10.7,6.3,3.8,13.5],"Alger County, Michigan":[10.1,57.6,10.8,6.5,1.9,13.1],"Allegan County, Michigan":[7.1,55.7,15.8,9.7,3,8.8],"Alpena County, Michigan":[14.6,45.4,12.9,10.3,5.3,11.5],"Antrim County, Michigan":[9.9,60.7,8.7,8.1,2.7,9.9],"Arenac County, Michigan":[11.6,47.8,15.6,9.3,3.7,12],"Baraga County, Michigan":[13.2,54.2,10.5,7.2,3.8,11.1],"Barry County, Michigan":[10.3,55.2,16.3,7.7,4,6.5],"Bay County, Michigan":[13.6,46.5,14.2,10,3.3,12.4],"Benzie County, Michigan":[8.2,54.9,15.5,8.2,4.4,8.7],"Berrien County, Michigan":[12.6,48.5,14.1,11.8,3.7,9.3],"Branch County, Michigan":[9.8,49.4,13.2,10.4,5,12.1],"Calhoun County, Michigan":[13.9,43.1,15.4,13.2,3.7,10.7],"Cass County, Michigan":[9.5,50.8,13.5,10.9,4.2,11.2],"Charlevoix County, Michigan":[12.5,56.8,6.9,8,1.9,13.9],"Cheboygan County, Michigan":[10.2,47.7,17.8,12.2,4.8,7.3],"Chippewa County, Michigan":[13.3,46.2,14.1,9.9,5.6,10.9],"Clare County, Michigan":[9.7,44.3,19.4,10.6,4.4,11.6],"Clinton County, Michigan":[9,54.7,12.5,8.1,7.5,8.2],"Crawford County, Michigan":[13.2,50,10.4,11.4,2.6,12.4],"Delta County, Michigan":[11.7,55.8,13.4,7.3,3.5,8.3],"Dickinson County, Michigan":[13.9,55.3,10,7.8,1.5,11.4],"Eaton County, Michigan":[12.2,51.6,13.2,8.9,3.8,10.3],"Emmet County, Michigan":[11.7,53.6,13.7,8.1,5.1,7.8],"Genesee County, Michigan":[12.3,42.3,15.9,13.9,4.1,11.4],"Gladwin County, Michigan":[10.3,56.8,11.8,9.2,3.3,8.6],"Gogebic County, Michigan":[20.9,46,11.4,8.1,2.8,10.8],"Grand Traverse County, Michigan":[10.9,50.2,14.2,8.4,5.5,10.9],"Gratiot County, Michigan":[9,52.5,12.3,8.7,5.1,12.4],"Hillsdale County, Michigan":[10.2,50.7,14.6,10.3,5.3,9],"Houghton County, Michigan":[13.8,45,10.3,7.5,12.5,10.9],"Huron County, Michigan":[14.9,51.8,13.1,7.5,2.4,10.3],"Ingham County, Michigan":[16.4,40.6,10.5,9.9,12.1,10.6],"Ionia County, Michigan":[8.8,45.2,18.6,11.4,6.4,9.5],"Iosco County, Michigan":[15.7,45.7,13.9,9.5,3.1,12.2],"Iron County, Michigan":[16.2,47.2,13.6,7.6,4.2,11.2],"Isabella County, Michigan":[12.9,38.6,11.1,8.2,15.8,13.3],"Jackson County, Michigan":[13.8,45.9,16.4,11.7,3.6,8.6],"Kalamazoo County, Michigan":[12.9,45.2,11.6,9.7,9.6,11.1],"Kalkaska County, Michigan":[11.5,51.7,10.3,7.6,4.1,14.8],"Kent County, Michigan":[10.5,50.3,12.4,10.7,6.8,9.3],"Keweenaw County, Michigan":[15.5,64.5,2.5,6.9,1.6,9],"Lake County, Michigan":[13.1,39.6,21.8,10.7,7.1,7.6],"Lapeer County, Michigan":[8.2,55.1,15.8,10.4,2.8,7.7],"Leelanau County, Michigan":[7,57,17.3,7.4,3.9,7.4],"Lenawee County, Michigan":[10.2,51.5,14.5,10,4,9.8],"Livingston County, Michigan":[7.7,58.5,16.6,7.1,3.3,6.9],"Luce County, Michigan":[13.6,51.3,9.8,6.9,1.8,16.6],"Mackinac County, Michigan":[17.4,48.4,9.6,6.7,5.9,11.9],"Macomb County, Michigan":[11.4,47.1,16.9,12.6,3.2,8.7],"Manistee County, Michigan":[11.3,49.5,15.8,9.2,4.2,10.1],"Marquette County, Michigan":[13.2,48.4,10.1,6.9,8.7,12.7],"Mason County, Michigan":[11.1,52.6,13.2,10.8,3.9,8.4],"Mecosta County, Michigan":[11.3,44.6,10,9.5,10.9,13.8],"Menominee County, Michigan":[13.4,47.1,16.5,9.7,3.6,9.7],"Midland County, Michigan":[11,56.1,12,8.5,3.4,9],"Missaukee County, Michigan":[7.6,54.1,16.6,8.4,3.3,10],"Monroe County, Michigan":[9.8,50.7,15.6,9.4,3.8,10.7],"Montcalm County, Michigan":[8.7,48.2,16.9,11.7,5,9.4],"Montmorency County, Michigan":[18.4,50.2,7.4,9.8,1.7,12.5],"Muskegon County, Michigan":[9.4,45.9,15,13.9,4.3,11.5],"Newaygo County, Michigan":[9.1,51.1,15.8,12.6,4.8,6.7],"Oakland County, Michigan":[12.8,50.6,15,9.5,4.1,8],"Oceana County, Michigan":[9,51,16.9,10.6,2.9,9.5],"Ogemaw County, Michigan":[12.4,49.7,13.5,10.1,3.5,10.9],"Ontonagon County, Michigan":[18.2,49.1,13.3,6.9,1.5,11],"Osceola County, Michigan":[10.4,51.2,13.4,9.8,4.7,10.5],"Oscoda County, Michigan":[11.7,53.4,12.8,7.3,1.6,13.1],"Otsego County, Michigan":[11.2,53.5,10.1,12.8,1.4,11.1],"Ottawa County, Michigan":[7.9,57.2,13.1,7.3,7.4,7.1],"Presque Isle County, Michigan":[14.4,56.3,10.3,7.6,1.5,9.8],"Roscommon County, Michigan":[15.2,49.5,9.5,10,4.4,11.4],"Saginaw County, Michigan":[12.6,44.2,15,12.4,5,10.8],"Sanilac County, Michigan":[11.8,55.9,11,7.5,2.5,11.2],"Schoolcraft County, Michigan":[12,53.9,7.3,8,3.3,15.6],"Shiawassee County, Michigan":[10.5,49.1,15.5,10.8,4,10.2],"St. Clair County, Michigan":[10.2,51.6,14.7,10.7,3.3,9.4],"St. Joseph County, Michigan":[9.9,48.7,14.2,12.1,3.7,11.3],"Tuscola County, Michigan":[10.7,50.7,16.1,8.8,3.6,10.2],"Van Buren County, Michigan":[9,51.6,13.9,12.8,3.4,9.3],"Washtenaw County, Michigan":[13.5,44.4,10.6,8.4,14.8,8.3],"Wayne County, Michigan":[14.1,36.3,19.8,17.6,4.6,7.6],"Wexford County, Michigan":[9,51.2,11.1,11.8,5.1,11.8]}
