[
  {
    "GEOID": "1000080",
    "NAME": "Appoquinimink",
    "population": 70195,
    "median_age": 39.9,
    "income": 53374,
    "median_rent": 1570,
    "median_home_value": 441300,
    "pct_white": 60.9189,
    "pct_black": 21.9987,
    "pct_asian": 8.7542,
    "pct_hispanic": 5.8181,
    "pct_poverty": 4.3846,
    "pct_bachelors_higher": 47.7
  },
  {
    "GEOID": "1000170",
    "NAME": "Cape Henlopen",
    "population": 65210,
    "median_age": 60.1,
    "income": 59908,
    "median_rent": 1472,
    "median_home_value": 469600,
    "pct_white": 86.6616,
    "pct_black": 4.2325,
    "pct_asian": 1.9767,
    "pct_hispanic": 4.484,
    "pct_poverty": 7.2087,
    "pct_bachelors_higher": 46.7
  },
  {
    "GEOID": "1000180",
    "NAME": "Caesar Rodney",
    "population": 49692,
    "median_age": 36.8,
    "income": 35867,
    "median_rent": 1591,
    "median_home_value": 319500,
    "pct_white": 62.1066,
    "pct_black": 24.5774,
    "pct_asian": 2.7167,
    "pct_hispanic": 6.3531,
    "pct_poverty": 9.9868,
    "pct_bachelors_higher": 33.8
  },
  {
    "GEOID": "1000190",
    "NAME": "Capital",
    "population": 60242,
    "median_age": 37.5,
    "income": 32317,
    "median_rent": 1231,
    "median_home_value": 265400,
    "pct_white": 46.9108,
    "pct_black": 36.4779,
    "pct_asian": 2.5298,
    "pct_hispanic": 11.2397,
    "pct_poverty": 15.3661,
    "pct_bachelors_higher": 24.1
  },
  {
    "GEOID": "1000200",
    "NAME": "Christina",
    "population": 179226,
    "median_age": 35,
    "income": 39803,
    "median_rent": 1436,
    "median_home_value": 292500,
    "pct_white": 50.6522,
    "pct_black": 28.0713,
    "pct_asian": 6.845,
    "pct_hispanic": 13.748,
    "pct_poverty": 13.8706,
    "pct_bachelors_higher": 35.8
  },
  {
    "GEOID": "1000230",
    "NAME": "Colonial",
    "population": 87503,
    "median_age": 39.9,
    "income": 40164,
    "median_rent": 1340,
    "median_home_value": 272000,
    "pct_white": 42.6557,
    "pct_black": 38.7484,
    "pct_asian": 4.5153,
    "pct_hispanic": 14.3321,
    "pct_poverty": 9.7359,
    "pct_bachelors_higher": 26.3
  },
  {
    "GEOID": "1000270",
    "NAME": "Delmar",
    "population": 7842,
    "median_age": 43.5,
    "income": 31845,
    "median_rent": 963,
    "median_home_value": 222900,
    "pct_white": 69.9439,
    "pct_black": 16.5774,
    "pct_asian": 1.5047,
    "pct_hispanic": 7.0518,
    "pct_poverty": 11.2645,
    "pct_bachelors_higher": 23.4
  },
  {
    "GEOID": "1000680",
    "NAME": "Indian River",
    "population": 94483,
    "median_age": 54.3,
    "income": 46146,
    "median_rent": 1324,
    "median_home_value": 368600,
    "pct_white": 78.1506,
    "pct_black": 6.7726,
    "pct_asian": 0.8721,
    "pct_hispanic": 13.957,
    "pct_poverty": 10.3113,
    "pct_bachelors_higher": 32.3
  },
  {
    "GEOID": "1000790",
    "NAME": "Lake Forest",
    "population": 26621,
    "median_age": 43.2,
    "income": 36025,
    "median_rent": 1209,
    "median_home_value": 269600,
    "pct_white": 78.9039,
    "pct_black": 13.2978,
    "pct_asian": 0.7287,
    "pct_hispanic": 4.4664,
    "pct_poverty": 9.1354,
    "pct_bachelors_higher": 25.5
  },
  {
    "GEOID": "1000810",
    "NAME": "Laurel",
    "population": 16731,
    "median_age": 36.9,
    "income": 30768,
    "median_rent": 920,
    "median_home_value": 246500,
    "pct_white": 72.2491,
    "pct_black": 16.2812,
    "pct_asian": 0.6216,
    "pct_hispanic": 12.8145,
    "pct_poverty": 17.3273,
    "pct_bachelors_higher": 14.6
  },
  {
    "GEOID": "1001080",
    "NAME": "Milford",
    "population": 34231,
    "median_age": 40.2,
    "income": 35169,
    "median_rent": 1160,
    "median_home_value": 289500,
    "pct_white": 63.5155,
    "pct_black": 21.4163,
    "pct_asian": 1.7703,
    "pct_hispanic": 11.1332,
    "pct_poverty": 14.3737,
    "pct_bachelors_higher": 24.2
  },
  {
    "GEOID": "1001240",
    "NAME": "Brandywine",
    "population": 92403,
    "median_age": 42.7,
    "income": 54395,
    "median_rent": 1368,
    "median_home_value": 365200,
    "pct_white": 65.2078,
    "pct_black": 23.1248,
    "pct_asian": 4.9652,
    "pct_hispanic": 4.8786,
    "pct_poverty": 7.4132,
    "pct_bachelors_higher": 47.5
  },
  {
    "GEOID": "1001300",
    "NAME": "Red Clay Consolidated",
    "population": 138038,
    "median_age": 42,
    "income": 53218,
    "median_rent": 1275,
    "median_home_value": 311900,
    "pct_white": 63.957,
    "pct_black": 16.4006,
    "pct_asian": 5.0588,
    "pct_hispanic": 14.0041,
    "pct_poverty": 10.7805,
    "pct_bachelors_higher": 42.7
  },
  {
    "GEOID": "1001530",
    "NAME": "Seaford",
    "population": 25341,
    "median_age": 42.9,
    "income": 31783,
    "median_rent": 1129,
    "median_home_value": 251200,
    "pct_white": 60.337,
    "pct_black": 21.116,
    "pct_asian": 0.88,
    "pct_hispanic": 11.2229,
    "pct_poverty": 17.0005,
    "pct_bachelors_higher": 19
  },
  {
    "GEOID": "1001620",
    "NAME": "Smyrna",
    "population": 40097,
    "median_age": 38.3,
    "income": 34940,
    "median_rent": 1395,
    "median_home_value": 316700,
    "pct_white": 63.2067,
    "pct_black": 25.6179,
    "pct_asian": 1.9677,
    "pct_hispanic": 7.7038,
    "pct_poverty": 6.5909,
    "pct_bachelors_higher": 22.7
  },
  {
    "GEOID": "1001850",
    "NAME": "Woodbridge",
    "population": 18017,
    "median_age": 39.5,
    "income": 32276,
    "median_rent": 1146,
    "median_home_value": 250000,
    "pct_white": 66.404,
    "pct_black": 17.2837,
    "pct_asian": 1.1545,
    "pct_hispanic": 16.9618,
    "pct_poverty": 18.1562,
    "pct_bachelors_higher": 17.8
  }
]
